{"15006":["US","15006","Bairdford","Pennsylvania","PA","Allegheny","003","","","40.6312","-79.8814","4"],"15007":["US","15007","Bakerstown","Pennsylvania","PA","Allegheny","003","","","40.6478","-79.931","4"],"15014":["US","15014","Brackenridge","Pennsylvania","PA","Allegheny","003","","","40.6082","-79.7414","4"],"15015":["US","15015","Bradfordwoods","Pennsylvania","PA","Allegheny","003","","","40.6372","-80.0811","1"],"15017":["US","15017","Bridgeville","Pennsylvania","PA","Allegheny","003","","","40.3472","-80.1153","4"],"15018":["US","15018","Buena Vista","Pennsylvania","PA","Allegheny","003","","","40.2773","-79.7992","4"],"15020":["US","15020","Bunola","Pennsylvania","PA","Allegheny","003","","","40.2373","-79.9506","4"],"15024":["US","15024","Cheswick","Pennsylvania","PA","Allegheny","003","","","40.5681","-79.841","4"],"15025":["US","15025","Clairton","Pennsylvania","PA","Allegheny","003","","","40.3243","-79.9317","4"],"15026":["US","15026","Clinton","Pennsylvania","PA","Allegheny","003","","","40.5131","-80.3423","4"],"15028":["US","15028","Coulters","Pennsylvania","PA","Allegheny","003","","","40.4344","-80.0248","1"],"15030":["US","15030","Creighton","Pennsylvania","PA","Allegheny","003","","","40.5821","-79.7818","4"],"15031":["US","15031","Cuddy","Pennsylvania","PA","Allegheny","003","","","40.3547","-80.1669","4"],"15032":["US","15032","Curtisville","Pennsylvania","PA","Allegheny","003","","","40.6423","-79.8509","4"],"15034":["US","15034","Dravosburg","Pennsylvania","PA","Allegheny","003","","","40.3527","-79.8895","4"],"15035":["US","15035","East Mc Keesport","Pennsylvania","PA","Allegheny","003","","","40.3839","-79.8079","1"],"15037":["US","15037","Elizabeth","Pennsylvania","PA","Allegheny","003","","","40.2656","-79.8568","4"],"15044":["US","15044","Gibsonia","Pennsylvania","PA","Allegheny","003","","","40.6252","-79.9443","4"],"15045":["US","15045","Glassport","Pennsylvania","PA","Allegheny","003","","","40.326","-79.8883","4"],"15046":["US","15046","Crescent","Pennsylvania","PA","Allegheny","003","","","40.5563","-80.2286","4"],"15047":["US","15047","Greenock","Pennsylvania","PA","Allegheny","003","","","40.3123","-79.8067","4"],"15049":["US","15049","Harwick","Pennsylvania","PA","Allegheny","003","","","40.5574","-79.8051","4"],"15051":["US","15051","Indianola","Pennsylvania","PA","Allegheny","003","","","40.5695","-79.8637","4"],"15056":["US","15056","Leetsdale","Pennsylvania","PA","Allegheny","003","","","40.5662","-80.2099","4"],"15064":["US","15064","Morgan","Pennsylvania","PA","Allegheny","003","","","40.3542","-80.1398","4"],"15065":["US","15065","Natrona Heights","Pennsylvania","PA","Allegheny","003","","","40.6421","-79.7273","4"],"15071":["US","15071","Oakdale","Pennsylvania","PA","Allegheny","003","","","40.4033","-80.1842","4"],"15075":["US","15075","Rural Ridge","Pennsylvania","PA","Allegheny","003","","","40.5856","-79.8287","4"],"15076":["US","15076","Russellton","Pennsylvania","PA","Allegheny","003","","","40.6073","-79.8347","4"],"15082":["US","15082","Sturgeon","Pennsylvania","PA","Allegheny","003","","","40.3863","-80.2083","4"],"15084":["US","15084","Tarentum","Pennsylvania","PA","Allegheny","003","","","40.6187","-79.7852","4"],"15086":["US","15086","Warrendale","Pennsylvania","PA","Allegheny","003","","","40.6534","-80.0795","4"],"15088":["US","15088","West Elizabeth","Pennsylvania","PA","Allegheny","003","","","40.2716","-79.8966","4"],"15090":["US","15090","Wexford","Pennsylvania","PA","Allegheny","003","","","40.612","-80.0649","4"],"15091":["US","15091","Wildwood","Pennsylvania","PA","Allegheny","003","","","40.5942","-79.9701","4"],"15095":["US","15095","Warrendale","Pennsylvania","PA","Allegheny","003","","","40.6534","-80.0795","4"],"15096":["US","15096","Warrendale","Pennsylvania","PA","Allegheny","003","","","40.6534","-80.0795","4"],"15101":["US","15101","Allison Park","Pennsylvania","PA","Allegheny","003","","","40.57","-79.9665","4"],"15102":["US","15102","Bethel Park","Pennsylvania","PA","Allegheny","003","","","40.321","-80.0398","4"],"15104":["US","15104","Braddock","Pennsylvania","PA","Allegheny","003","","","40.4038","-79.8625","4"],"15106":["US","15106","Carnegie","Pennsylvania","PA","Allegheny","003","","","40.4029","-80.0915","4"],"15108":["US","15108","Coraopolis","Pennsylvania","PA","Allegheny","003","","","40.5","-80.1996","4"],"15110":["US","15110","Duquesne","Pennsylvania","PA","Allegheny","003","","","40.3704","-79.8522","4"],"15112":["US","15112","East Pittsburgh","Pennsylvania","PA","Allegheny","003","","","40.4036","-79.8389","4"],"15116":["US","15116","Glenshaw","Pennsylvania","PA","Allegheny","003","","","40.5375","-79.9644","4"],"15120":["US","15120","Homestead","Pennsylvania","PA","Allegheny","003","","","40.3926","-79.9052","4"],"15122":["US","15122","West Mifflin","Pennsylvania","PA","Allegheny","003","","","40.3634","-79.8664","4"],"15123":["US","15123","West Mifflin","Pennsylvania","PA","Allegheny","003","","","40.4344","-80.0248","4"],"15126":["US","15126","Imperial","Pennsylvania","PA","Allegheny","003","","","40.4584","-80.2649","4"],"15127":["US","15127","Ingomar","Pennsylvania","PA","Allegheny","003","","","40.5809","-80.0609","4"],"15129":["US","15129","South Park","Pennsylvania","PA","Allegheny","003","","","40.2932","-79.996","4"],"15131":["US","15131","Mckeesport","Pennsylvania","PA","Allegheny","003","","","40.3478","-79.8642","4"],"15132":["US","15132","Mckeesport","Pennsylvania","PA","Allegheny","003","","","40.3478","-79.8642","4"],"15133":["US","15133","Mckeesport","Pennsylvania","PA","Allegheny","003","","","40.3478","-79.8642","4"],"15134":["US","15134","Mckeesport","Pennsylvania","PA","Allegheny","003","","","40.3478","-79.8642","4"],"15135":["US","15135","Mckeesport","Pennsylvania","PA","Allegheny","003","","","40.3478","-79.8642","4"],"15136":["US","15136","Mc Kees Rocks","Pennsylvania","PA","Allegheny","003","","","40.4717","-80.0876","1"],"15137":["US","15137","North Versailles","Pennsylvania","PA","Allegheny","003","","","40.3762","-79.8124","4"],"15139":["US","15139","Oakmont","Pennsylvania","PA","Allegheny","003","","","40.5196","-79.8369","4"],"15140":["US","15140","Pitcairn","Pennsylvania","PA","Allegheny","003","","","40.4048","-79.777","4"],"15142":["US","15142","Presto","Pennsylvania","PA","Allegheny","003","","","40.3847","-80.1209","4"],"15143":["US","15143","Sewickley","Pennsylvania","PA","Allegheny","003","","","40.557","-80.1578","4"],"15144":["US","15144","Springdale","Pennsylvania","PA","Allegheny","003","","","40.544","-79.7844","4"],"15145":["US","15145","Turtle Creek","Pennsylvania","PA","Allegheny","003","","","40.4113","-79.822","4"],"15146":["US","15146","Monroeville","Pennsylvania","PA","Allegheny","003","","","40.429","-79.7623","4"],"15147":["US","15147","Verona","Pennsylvania","PA","Allegheny","003","","","40.4927","-79.8345","4"],"15148":["US","15148","Wilmerding","Pennsylvania","PA","Allegheny","003","","","40.3934","-79.7951","4"],"15201":["US","15201","Pittsburgh","Pennsylvania","PA","Allegheny","003","","","40.4752","-79.9528","4"],"15202":["US","15202","Pittsburgh","Pennsylvania","PA","Allegheny","003","","","40.5053","-80.0685","4"],"15203":["US","15203","Pittsburgh","Pennsylvania","PA","Allegheny","003","","","40.4254","-79.9799","4"],"15204":["US","15204","Pittsburgh","Pennsylvania","PA","Allegheny","003","","","40.4554","-80.0644","4"],"15205":["US","15205","Pittsburgh","Pennsylvania","PA","Allegheny","003","","","40.4322","-80.1021","4"],"15206":["US","15206","Pittsburgh","Pennsylvania","PA","Allegheny","003","","","40.4723","-79.9132","4"],"15207":["US","15207","Pittsburgh","Pennsylvania","PA","Allegheny","003","","","40.4003","-79.9338","4"],"15208":["US","15208","Pittsburgh","Pennsylvania","PA","Allegheny","003","","","40.4532","-79.8995","4"],"15209":["US","15209","Pittsburgh","Pennsylvania","PA","Allegheny","003","","","40.4999","-79.9739","4"],"15210":["US","15210","Pittsburgh","Pennsylvania","PA","Allegheny","003","","","40.4072","-79.9839","4"],"15211":["US","15211","Pittsburgh","Pennsylvania","PA","Allegheny","003","","","40.4295","-80.0144","4"],"15212":["US","15212","Pittsburgh","Pennsylvania","PA","Allegheny","003","","","40.4406","-79.9959","4"],"15213":["US","15213","Pittsburgh","Pennsylvania","PA","Allegheny","003","","","40.444","-79.9552","4"],"15214":["US","15214","Pittsburgh","Pennsylvania","PA","Allegheny","003","","","40.4865","-80.014","4"],"15215":["US","15215","Pittsburgh","Pennsylvania","PA","Allegheny","003","","","40.5048","-79.9138","4"],"15216":["US","15216","Pittsburgh","Pennsylvania","PA","Allegheny","003","","","40.4001","-80.0462","4"],"15217":["US","15217","Pittsburgh","Pennsylvania","PA","Allegheny","003","","","40.4308","-79.9205","4"],"15218":["US","15218","Pittsburgh","Pennsylvania","PA","Allegheny","003","","","40.4237","-79.89","4"],"15219":["US","15219","Pittsburgh","Pennsylvania","PA","Allegheny","003","","","40.4423","-79.983","4"],"15220":["US","15220","Pittsburgh","Pennsylvania","PA","Allegheny","003","","","40.4181","-80.0526","4"],"15221":["US","15221","Pittsburgh","Pennsylvania","PA","Allegheny","003","","","40.4346","-79.8655","4"],"15222":["US","15222","Pittsburgh","Pennsylvania","PA","Allegheny","003","","","40.4477","-79.9933","4"],"15223":["US","15223","Pittsburgh","Pennsylvania","PA","Allegheny","003","","","40.5051","-79.9528","4"],"15224":["US","15224","Pittsburgh","Pennsylvania","PA","Allegheny","003","","","40.4642","-79.9448","4"],"15225":["US","15225","Pittsburgh","Pennsylvania","PA","Allegheny","003","","","40.5051","-80.1155","4"],"15226":["US","15226","Pittsburgh","Pennsylvania","PA","Allegheny","003","","","40.4001","-80.0161","4"],"15227":["US","15227","Pittsburgh","Pennsylvania","PA","Allegheny","003","","","40.3805","-79.9667","4"],"15228":["US","15228","Pittsburgh","Pennsylvania","PA","Allegheny","003","","","40.3696","-80.0439","4"],"15229":["US","15229","Pittsburgh","Pennsylvania","PA","Allegheny","003","","","40.5203","-80.037","4"],"15230":["US","15230","Pittsburgh","Pennsylvania","PA","Allegheny","003","","","40.4344","-80.0248","4"],"15231":["US","15231","Pittsburgh","Pennsylvania","PA","Allegheny","003","","","40.4961","-80.2466","4"],"15232":["US","15232","Pittsburgh","Pennsylvania","PA","Allegheny","003","","","40.4525","-79.9319","4"],"15233":["US","15233","Pittsburgh","Pennsylvania","PA","Allegheny","003","","","40.4608","-80.0348","4"],"15234":["US","15234","Pittsburgh","Pennsylvania","PA","Allegheny","003","","","40.3688","-80.0224","4"],"15235":["US","15235","Pittsburgh","Pennsylvania","PA","Allegheny","003","","","40.4598","-79.8224","4"],"15236":["US","15236","Pittsburgh","Pennsylvania","PA","Allegheny","003","","","40.3351","-79.9832","4"],"15237":["US","15237","Pittsburgh","Pennsylvania","PA","Allegheny","003","","","40.5488","-80.0474","4"],"15238":["US","15238","Pittsburgh","Pennsylvania","PA","Allegheny","003","","","40.5346","-79.8805","4"],"15239":["US","15239","Pittsburgh","Pennsylvania","PA","Allegheny","003","","","40.4837","-79.7381","4"],"15240":["US","15240","Pittsburgh","Pennsylvania","PA","Allegheny","003","","","40.4344","-80.0248","4"],"15241":["US","15241","Pittsburgh","Pennsylvania","PA","Allegheny","003","","","40.3323","-80.081","4"],"15242":["US","15242","Pittsburgh","Pennsylvania","PA","Allegheny","003","","","40.4344","-80.0248","4"],"15243":["US","15243","Pittsburgh","Pennsylvania","PA","Allegheny","003","","","40.3748","-80.0731","4"],"15244":["US","15244","Pittsburgh","Pennsylvania","PA","Allegheny","003","","","40.4344","-80.0248","4"],"15250":["US","15250","Pittsburgh","Pennsylvania","PA","Allegheny","003","","","40.4344","-80.0248","4"],"15251":["US","15251","Pittsburgh","Pennsylvania","PA","Allegheny","003","","","40.4344","-80.0248","4"],"15252":["US","15252","Pittsburgh","Pennsylvania","PA","Allegheny","003","","","40.4344","-80.0248","4"],"15253":["US","15253","Pittsburgh","Pennsylvania","PA","Allegheny","003","","","40.4344","-80.0248","4"],"15254":["US","15254","Pittsburgh","Pennsylvania","PA","Allegheny","003","","","40.4344","-80.0248","4"],"15255":["US","15255","Pittsburgh","Pennsylvania","PA","Allegheny","003","","","40.4344","-80.0248","4"],"15257":["US","15257","Pittsburgh","Pennsylvania","PA","Allegheny","003","","","40.4344","-80.0248","4"],"15258":["US","15258","Pittsburgh","Pennsylvania","PA","Allegheny","003","","","40.4344","-80.0248","4"],"15259":["US","15259","Pittsburgh","Pennsylvania","PA","Allegheny","003","","","40.4344","-80.0248","4"],"15260":["US","15260","Pittsburgh","Pennsylvania","PA","Allegheny","003","","","40.4432","-79.9531","4"],"15261":["US","15261","Pittsburgh","Pennsylvania","PA","Allegheny","003","","","40.4344","-80.0248","4"],"15262":["US","15262","Pittsburgh","Pennsylvania","PA","Allegheny","003","","","40.4344","-80.0248","4"],"15264":["US","15264","Pittsburgh","Pennsylvania","PA","Allegheny","003","","","40.4344","-80.0248","4"],"15265":["US","15265","Pittsburgh","Pennsylvania","PA","Allegheny","003","","","40.4344","-80.0248","4"],"15267":["US","15267","Pittsburgh","Pennsylvania","PA","Allegheny","003","","","40.4344","-80.0248","4"],"15268":["US","15268","Pittsburgh","Pennsylvania","PA","Allegheny","003","","","40.4344","-80.0248","4"],"15270":["US","15270","Pittsburgh","Pennsylvania","PA","Allegheny","003","","","40.4344","-80.0248","4"],"15272":["US","15272","Pittsburgh","Pennsylvania","PA","Allegheny","003","","","40.4344","-80.0248","4"],"15274":["US","15274","Pittsburgh","Pennsylvania","PA","Allegheny","003","","","40.4344","-80.0248","4"],"15275":["US","15275","Pittsburgh","Pennsylvania","PA","Allegheny","003","","","40.4495","-80.1795","4"],"15276":["US","15276","Pittsburgh","Pennsylvania","PA","Allegheny","003","","","40.4344","-80.0248","4"],"15277":["US","15277","Pittsburgh","Pennsylvania","PA","Allegheny","003","","","40.4344","-80.0248","4"],"15278":["US","15278","Pittsburgh","Pennsylvania","PA","Allegheny","003","","","40.4344","-80.0248","4"],"15279":["US","15279","Pittsburgh","Pennsylvania","PA","Allegheny","003","","","40.4344","-80.0248","4"],"15281":["US","15281","Pittsburgh","Pennsylvania","PA","Allegheny","003","","","40.4344","-80.0248","4"],"15282":["US","15282","Pittsburgh","Pennsylvania","PA","Allegheny","003","","","40.4406","-79.9959","4"],"15283":["US","15283","Pittsburgh","Pennsylvania","PA","Allegheny","003","","","40.4344","-80.0248","4"],"15286":["US","15286","Pittsburgh","Pennsylvania","PA","Allegheny","003","","","40.4344","-80.0248","4"],"15289":["US","15289","Pittsburgh","Pennsylvania","PA","Allegheny","003","","","40.4446","-79.9451","4"],"15290":["US","15290","Pittsburgh","Pennsylvania","PA","Allegheny","003","","","40.4344","-80.0248","4"],"15295":["US","15295","Pittsburgh","Pennsylvania","PA","Allegheny","003","","","40.463","-80.0108","4"],"15656":["US","15656","Leechburg","Pennsylvania","PA","Armstrong","005","","","40.6344","-79.6201","4"],"15673":["US","15673","North Apollo","Pennsylvania","PA","Armstrong","005","","","40.593","-79.5581","4"],"15682":["US","15682","Schenley","Pennsylvania","PA","Armstrong","005","","","40.6845","-79.6617","4"],"15686":["US","15686","Spring Church","Pennsylvania","PA","Armstrong","005","","","40.6153","-79.4545","4"],"15736":["US","15736","Elderton","Pennsylvania","PA","Armstrong","005","","","40.6922","-79.3422","4"],"15774":["US","15774","Shelocta","Pennsylvania","PA","Armstrong","005","","","40.6388","-79.3191","4"],"15001":["US","15001","Aliquippa","Pennsylvania","PA","Beaver","007","","","40.5921","-80.3197","4"],"15003":["US","15003","Ambridge","Pennsylvania","PA","Beaver","007","","","40.6005","-80.2105","4"],"15005":["US","15005","Baden","Pennsylvania","PA","Beaver","007","","","40.6416","-80.1985","4"],"15009":["US","15009","Beaver","Pennsylvania","PA","Beaver","007","","","40.6972","-80.3365","4"],"15010":["US","15010","Beaver Falls","Pennsylvania","PA","Beaver","007","","","40.7687","-80.3592","4"],"15027":["US","15027","Conway","Pennsylvania","PA","Beaver","007","","","40.6649","-80.2349","4"],"15042":["US","15042","Freedom","Pennsylvania","PA","Beaver","007","","","40.683","-80.2147","4"],"15043":["US","15043","Georgetown","Pennsylvania","PA","Beaver","007","","","40.5743","-80.49","4"],"15050":["US","15050","Hookstown","Pennsylvania","PA","Beaver","007","","","40.5622","-80.4388","4"],"15052":["US","15052","Industry","Pennsylvania","PA","Beaver","007","","","40.6671","-80.4151","4"],"15059":["US","15059","Midland","Pennsylvania","PA","Beaver","007","","","40.6793","-80.4908","4"],"15061":["US","15061","Monaca","Pennsylvania","PA","Beaver","007","","","40.6718","-80.2917","4"],"15066":["US","15066","New Brighton","Pennsylvania","PA","Beaver","007","","","40.7393","-80.2972","4"],"15074":["US","15074","Rochester","Pennsylvania","PA","Beaver","007","","","40.7157","-80.2603","4"],"15077":["US","15077","Shippingport","Pennsylvania","PA","Beaver","007","","","40.632","-80.414","4"],"15081":["US","15081","South Heights","Pennsylvania","PA","Beaver","007","","","40.5763","-80.2383","4"],"15521":["US","15521","Alum Bank","Pennsylvania","PA","Bedford","009","","","40.1858","-78.6206","4"],"15522":["US","15522","Bedford","Pennsylvania","PA","Bedford","009","","","39.9908","-78.5261","4"],"15533":["US","15533","Breezewood","Pennsylvania","PA","Bedford","009","","","39.9905","-78.2453","4"],"15534":["US","15534","Buffalo Mills","Pennsylvania","PA","Bedford","009","","","39.922","-78.6996","4"],"15535":["US","15535","Clearville","Pennsylvania","PA","Bedford","009","","","39.8533","-78.4392","4"],"15537":["US","15537","Everett","Pennsylvania","PA","Bedford","009","","","40.0098","-78.3713","4"],"15539":["US","15539","Fishertown","Pennsylvania","PA","Bedford","009","","","40.1217","-78.5856","4"],"15545":["US","15545","Hyndman","Pennsylvania","PA","Bedford","009","","","39.8049","-78.7335","4"],"15550":["US","15550","Manns Choice","Pennsylvania","PA","Bedford","009","","","39.9808","-78.6423","4"],"15554":["US","15554","New Paris","Pennsylvania","PA","Bedford","009","","","40.1254","-78.6184","4"],"15559":["US","15559","Schellsburg","Pennsylvania","PA","Bedford","009","","","40.0487","-78.6482","4"],"15714":["US","15714","Northern Cambria","Pennsylvania","PA","Cambria","021","","","40.6661","-78.792","4"],"15722":["US","15722","Carrolltown","Pennsylvania","PA","Cambria","021","","","40.5891","-78.7037","4"],"15737":["US","15737","Elmora","Pennsylvania","PA","Cambria","021","","","40.6076","-78.7524","4"],"15738":["US","15738","Emeigh","Pennsylvania","PA","Cambria","021","","","40.6948","-78.787","4"],"15760":["US","15760","Marsteller","Pennsylvania","PA","Cambria","021","","","40.6522","-78.8054","4"],"15762":["US","15762","Nicktown","Pennsylvania","PA","Cambria","021","","","40.6016","-78.8114","4"],"15773":["US","15773","Saint Benedict","Pennsylvania","PA","Cambria","021","","","40.6298","-78.7329","4"],"15775":["US","15775","Spangler","Pennsylvania","PA","Cambria","021","","","40.6351","-78.7692","4"],"15901":["US","15901","Johnstown","Pennsylvania","PA","Cambria","021","","","40.326","-78.9141","4"],"15902":["US","15902","Johnstown","Pennsylvania","PA","Cambria","021","","","40.3078","-78.8969","4"],"15904":["US","15904","Johnstown","Pennsylvania","PA","Cambria","021","","","40.285","-78.8654","4"],"15905":["US","15905","Johnstown","Pennsylvania","PA","Cambria","021","","","40.3072","-78.943","4"],"15906":["US","15906","Johnstown","Pennsylvania","PA","Cambria","021","","","40.3522","-78.9383","4"],"15907":["US","15907","Johnstown","Pennsylvania","PA","Cambria","021","","","40.3254","-78.9151","4"],"15909":["US","15909","Johnstown","Pennsylvania","PA","Cambria","021","","","40.4096","-78.8712","4"],"15915":["US","15915","Johnstown","Pennsylvania","PA","Cambria","021","","","40.3267","-78.922","4"],"15921":["US","15921","Beaverdale","Pennsylvania","PA","Cambria","021","","","40.3173","-78.7009","4"],"15922":["US","15922","Belsano","Pennsylvania","PA","Cambria","021","","","40.5176","-78.8767","4"],"15925":["US","15925","Cassandra","Pennsylvania","PA","Cambria","021","","","40.4085","-78.6407","4"],"15927":["US","15927","Colver","Pennsylvania","PA","Cambria","021","","","40.5383","-78.7865","4"],"15930":["US","15930","Dunlo","Pennsylvania","PA","Cambria","021","","","40.2939","-78.7192","4"],"15931":["US","15931","Ebensburg","Pennsylvania","PA","Cambria","021","","","40.4801","-78.7263","4"],"15934":["US","15934","Elton","Pennsylvania","PA","Cambria","021","","","40.2799","-78.8032","4"],"15938":["US","15938","Lilly","Pennsylvania","PA","Cambria","021","","","40.4238","-78.6231","4"],"15940":["US","15940","Loretto","Pennsylvania","PA","Cambria","021","","","40.5105","-78.6294","4"],"15942":["US","15942","Mineral Point","Pennsylvania","PA","Cambria","021","","","40.3793","-78.8352","4"],"15943":["US","15943","Nanty Glo","Pennsylvania","PA","Cambria","021","","","40.4704","-78.8375","4"],"15945":["US","15945","Parkhill","Pennsylvania","PA","Cambria","021","","","40.3612","-78.8709","4"],"15946":["US","15946","Portage","Pennsylvania","PA","Cambria","021","","","40.3724","-78.6328","4"],"15948":["US","15948","Revloc","Pennsylvania","PA","Cambria","021","","","40.49","-78.7646","4"],"15951":["US","15951","Saint Michael","Pennsylvania","PA","Cambria","021","","","40.337","-78.7709","4"],"15952":["US","15952","Salix","Pennsylvania","PA","Cambria","021","","","40.2986","-78.7816","4"],"15955":["US","15955","Sidman","Pennsylvania","PA","Cambria","021","","","40.3299","-78.746","4"],"15956":["US","15956","South Fork","Pennsylvania","PA","Cambria","021","","","40.3629","-78.7887","4"],"15958":["US","15958","Summerhill","Pennsylvania","PA","Cambria","021","","","40.389","-78.756","4"],"15960":["US","15960","Twin Rocks","Pennsylvania","PA","Cambria","021","","","40.4967","-78.8659","4"],"15961":["US","15961","Vintondale","Pennsylvania","PA","Cambria","021","","","40.4939","-78.9427","4"],"15962":["US","15962","Wilmore","Pennsylvania","PA","Cambria","021","","","40.3887","-78.7186","4"],"15832":["US","15832","Driftwood","Pennsylvania","PA","Cameron","023","","","41.3764","-78.1632","4"],"15834":["US","15834","Emporium","Pennsylvania","PA","Cameron","023","","","41.5177","-78.2536","4"],"15861":["US","15861","Sinnamahoning","Pennsylvania","PA","Cameron","023","","","41.3762","-78.0661","1"],"15721":["US","15721","Burnside","Pennsylvania","PA","Clearfield","033","","","40.8134","-78.7865","4"],"15753":["US","15753","La Jose","Pennsylvania","PA","Clearfield","033","","","40.7876","-78.6514","1"],"15757":["US","15757","Mahaffey","Pennsylvania","PA","Clearfield","033","","","40.8875","-78.7353","4"],"15801":["US","15801","Du Bois","Pennsylvania","PA","Clearfield","033","","","41.126","-78.7527","1"],"15848":["US","15848","Luthersburg","Pennsylvania","PA","Clearfield","033","","","41.0532","-78.7428","4"],"15849":["US","15849","Penfield","Pennsylvania","PA","Clearfield","033","","","41.2085","-78.5791","4"],"15856":["US","15856","Rockton","Pennsylvania","PA","Clearfield","033","","","41.0806","-78.6577","4"],"15866":["US","15866","Troutville","Pennsylvania","PA","Clearfield","033","","","41.0256","-78.7853","4"],"15821":["US","15821","Benezett","Pennsylvania","PA","Elk","047","","","41.3253","-78.3576","1"],"15822":["US","15822","Brandy Camp","Pennsylvania","PA","Elk","047","","","41.3209","-78.6875","4"],"15823":["US","15823","Brockport","Pennsylvania","PA","Elk","047","","","41.2822","-78.7128","4"],"15827":["US","15827","Byrnedale","Pennsylvania","PA","Elk","047","","","41.2865","-78.5051","4"],"15831":["US","15831","Dagus Mines","Pennsylvania","PA","Elk","047","","","41.3539","-78.6056","4"],"15841":["US","15841","Force","Pennsylvania","PA","Elk","047","","","41.2629","-78.5298","4"],"15845":["US","15845","Johnsonburg","Pennsylvania","PA","Elk","047","","","41.4928","-78.6783","4"],"15846":["US","15846","Kersey","Pennsylvania","PA","Elk","047","","","41.3563","-78.6015","4"],"15853":["US","15853","Ridgway","Pennsylvania","PA","Elk","047","","","41.3621","-78.7262","4"],"15857":["US","15857","Saint Marys","Pennsylvania","PA","Elk","047","","","41.4289","-78.5505","4"],"15868":["US","15868","Weedville","Pennsylvania","PA","Elk","047","","","41.2685","-78.4952","4"],"15870":["US","15870","Wilcox","Pennsylvania","PA","Elk","047","","","41.5735","-78.6823","4"],"15012":["US","15012","Belle Vernon","Pennsylvania","PA","Fayette","051","","","40.1588","-79.8122","4"],"15401":["US","15401","Uniontown","Pennsylvania","PA","Fayette","051","","","39.8897","-79.7282","4"],"15410":["US","15410","Adah","Pennsylvania","PA","Fayette","051","","","39.8965","-79.922","4"],"15413":["US","15413","Allison","Pennsylvania","PA","Fayette","051","","","39.9868","-79.8637","4"],"15415":["US","15415","Brier Hill","Pennsylvania","PA","Fayette","051","","","39.9808","-79.8504","4"],"15416":["US","15416","Brownfield","Pennsylvania","PA","Fayette","051","","","39.857","-79.712","4"],"15417":["US","15417","Brownsville","Pennsylvania","PA","Fayette","051","","","40.0237","-79.8839","4"],"15420":["US","15420","Cardale","Pennsylvania","PA","Fayette","051","","","39.9567","-79.8662","4"],"15421":["US","15421","Chalk Hill","Pennsylvania","PA","Fayette","051","","","39.8451","-79.5991","1"],"15422":["US","15422","Chestnut Ridge","Pennsylvania","PA","Fayette","051","","","39.9812","-79.8116","4"],"15425":["US","15425","Connellsville","Pennsylvania","PA","Fayette","051","","","40.0265","-79.5566","4"],"15428":["US","15428","Dawson","Pennsylvania","PA","Fayette","051","","","40.0638","-79.6602","4"],"15430":["US","15430","Dickerson Run","Pennsylvania","PA","Fayette","051","","","40.0418","-79.66","4"],"15431":["US","15431","Dunbar","Pennsylvania","PA","Fayette","051","","","39.9722","-79.6431","4"],"15433":["US","15433","East Millsboro","Pennsylvania","PA","Fayette","051","","","39.9822","-79.9664","4"],"15435":["US","15435","Fairbank","Pennsylvania","PA","Fayette","051","","","39.9434","-79.8495","4"],"15436":["US","15436","Fairchance","Pennsylvania","PA","Fayette","051","","","39.8229","-79.7551","4"],"15437":["US","15437","Farmington","Pennsylvania","PA","Fayette","051","","","39.807","-79.5832","4"],"15438":["US","15438","Fayette City","Pennsylvania","PA","Fayette","051","","","40.0988","-79.8366","4"],"15439":["US","15439","Gans","Pennsylvania","PA","Fayette","051","","","39.7429","-79.8242","4"],"15440":["US","15440","Gibbon Glade","Pennsylvania","PA","Fayette","051","","","39.7364","-79.5736","4"],"15442":["US","15442","Grindstone","Pennsylvania","PA","Fayette","051","","","40.0084","-79.8404","4"],"15443":["US","15443","Hibbs","Pennsylvania","PA","Fayette","051","","","39.9317","-79.8825","4"],"15444":["US","15444","Hiller","Pennsylvania","PA","Fayette","051","","","40.012","-79.9088","4"],"15445":["US","15445","Hopwood","Pennsylvania","PA","Fayette","051","","","39.8728","-79.6568","4"],"15446":["US","15446","Indian Head","Pennsylvania","PA","Fayette","051","","","40.0248","-79.395","4"],"15447":["US","15447","Isabella","Pennsylvania","PA","Fayette","051","","","39.946","-79.9393","4"],"15449":["US","15449","Keisterville","Pennsylvania","PA","Fayette","051","","","39.9636","-79.7853","4"],"15450":["US","15450","La Belle","Pennsylvania","PA","Fayette","051","","","39.9983","-79.9754","4"],"15451":["US","15451","Lake Lynn","Pennsylvania","PA","Fayette","051","","","39.7501","-79.8618","4"],"15454":["US","15454","Leckrone","Pennsylvania","PA","Fayette","051","","","39.8615","-79.8701","4"],"15455":["US","15455","Leisenring","Pennsylvania","PA","Fayette","051","","","39.9985","-79.6435","4"],"15456":["US","15456","Lemont Furnace","Pennsylvania","PA","Fayette","051","","","39.9311","-79.6477","4"],"15458":["US","15458","Mc Clellandtown","Pennsylvania","PA","Fayette","051","","","39.8882","-79.8694","1"],"15459":["US","15459","Markleysburg","Pennsylvania","PA","Fayette","051","","","39.7597","-79.46","4"],"15460":["US","15460","Martin","Pennsylvania","PA","Fayette","051","","","39.8065","-79.9098","4"],"15461":["US","15461","Masontown","Pennsylvania","PA","Fayette","051","","","39.8424","-79.9003","4"],"15462":["US","15462","Melcroft","Pennsylvania","PA","Fayette","051","","","40.052","-79.3892","4"],"15463":["US","15463","Merrittstown","Pennsylvania","PA","Fayette","051","","","39.8825","-79.8336","4"],"15464":["US","15464","Mill Run","Pennsylvania","PA","Fayette","051","","","39.968","-79.4622","4"],"15465":["US","15465","Mount Braddock","Pennsylvania","PA","Fayette","051","","","39.9321","-79.6522","4"],"15466":["US","15466","Newell","Pennsylvania","PA","Fayette","051","","","40.0751","-79.8943","4"],"15467":["US","15467","New Geneva","Pennsylvania","PA","Fayette","051","","","39.7884","-79.9092","4"],"15468":["US","15468","New Salem","Pennsylvania","PA","Fayette","051","","","39.9242","-79.8356","4"],"15469":["US","15469","Normalville","Pennsylvania","PA","Fayette","051","","","40.0418","-79.4151","4"],"15470":["US","15470","Ohiopyle","Pennsylvania","PA","Fayette","051","","","39.8507","-79.523","4"],"15472":["US","15472","Oliver","Pennsylvania","PA","Fayette","051","","","39.9183","-79.7158","4"],"15473":["US","15473","Perryopolis","Pennsylvania","PA","Fayette","051","","","40.0646","-79.7756","4"],"15474":["US","15474","Point Marion","Pennsylvania","PA","Fayette","051","","","39.7351","-79.899","4"],"15475":["US","15475","Republic","Pennsylvania","PA","Fayette","051","","","39.9626","-79.8767","4"],"15476":["US","15476","Ronco","Pennsylvania","PA","Fayette","051","","","39.8697","-79.9206","4"],"15478":["US","15478","Smithfield","Pennsylvania","PA","Fayette","051","","","39.7923","-79.8127","4"],"15480":["US","15480","Smock","Pennsylvania","PA","Fayette","051","","","39.9961","-79.7678","4"],"15482":["US","15482","Star Junction","Pennsylvania","PA","Fayette","051","","","40.0651","-79.769","4"],"15484":["US","15484","Uledi","Pennsylvania","PA","Fayette","051","","","39.8936","-79.7856","4"],"15486":["US","15486","Vanderbilt","Pennsylvania","PA","Fayette","051","","","40.0246","-79.6955","4"],"15488":["US","15488","Waltersburg","Pennsylvania","PA","Fayette","051","","","39.9763","-79.7689","4"],"15489":["US","15489","West Leisenring","Pennsylvania","PA","Fayette","051","","","39.9561","-79.7007","4"],"15490":["US","15490","White","Pennsylvania","PA","Fayette","051","","","40.0726","-79.4251","4"],"15492":["US","15492","Wickhaven","Pennsylvania","PA","Fayette","051","","","40.1194","-79.7623","4"],"15631":["US","15631","Everson","Pennsylvania","PA","Fayette","051","","","40.0911","-79.5873","4"],"15828":["US","15828","Clarington","Pennsylvania","PA","Forest","053","","","41.3233","-79.1466","4"],"15536":["US","15536","Crystal Spring","Pennsylvania","PA","Fulton","057","","","39.92","-78.2258","4"],"15310":["US","15310","Aleppo","Pennsylvania","PA","Greene","059","","","39.8246","-80.4579","4"],"15315":["US","15315","Bobtown","Pennsylvania","PA","Greene","059","","","39.7612","-79.9814","4"],"15316":["US","15316","Brave","Pennsylvania","PA","Greene","059","","","39.7245","-80.2537","4"],"15320":["US","15320","Carmichaels","Pennsylvania","PA","Greene","059","","","39.8825","-79.971","4"],"15322":["US","15322","Clarksville","Pennsylvania","PA","Greene","059","","","39.9667","-80.0452","4"],"15325":["US","15325","Crucible","Pennsylvania","PA","Greene","059","","","39.9502","-79.9676","4"],"15327":["US","15327","Dilliner","Pennsylvania","PA","Greene","059","","","39.7555","-79.9771","4"],"15334":["US","15334","Garards Fort","Pennsylvania","PA","Greene","059","","","39.8083","-79.9679","4"],"15337":["US","15337","Graysville","Pennsylvania","PA","Greene","059","","","39.9092","-80.3952","4"],"15338":["US","15338","Greensboro","Pennsylvania","PA","Greene","059","","","39.8045","-79.9399","4"],"15341":["US","15341","Holbrook","Pennsylvania","PA","Greene","059","","","39.8489","-80.3385","4"],"15344":["US","15344","Jefferson","Pennsylvania","PA","Greene","059","","","39.9334","-80.0503","4"],"15346":["US","15346","Mather","Pennsylvania","PA","Greene","059","","","39.9354","-80.0753","4"],"15349":["US","15349","Mount Morris","Pennsylvania","PA","Greene","059","","","39.774","-80.0246","4"],"15351":["US","15351","Nemacolin","Pennsylvania","PA","Greene","059","","","39.8779","-79.9258","4"],"15352":["US","15352","New Freeport","Pennsylvania","PA","Greene","059","","","39.7507","-80.4542","4"],"15353":["US","15353","Nineveh","Pennsylvania","PA","Greene","059","","","39.9615","-80.3078","4"],"15357":["US","15357","Rices Landing","Pennsylvania","PA","Greene","059","","","39.944","-79.9857","4"],"15359":["US","15359","Rogersville","Pennsylvania","PA","Greene","059","","","39.8765","-80.2758","4"],"15362":["US","15362","Spraggs","Pennsylvania","PA","Greene","059","","","39.7447","-80.2145","4"],"15364":["US","15364","Sycamore","Pennsylvania","PA","Greene","059","","","39.9415","-80.2906","4"],"15370":["US","15370","Waynesburg","Pennsylvania","PA","Greene","059","","","39.8917","-80.1795","4"],"15380":["US","15380","Wind Ridge","Pennsylvania","PA","Greene","059","","","39.8971","-80.4647","4"],"15681":["US","15681","Saltsburg","Pennsylvania","PA","Indiana","063","","","40.5429","-79.3978","4"],"15701":["US","15701","Indiana","Pennsylvania","PA","Indiana","063","","","40.6196","-79.1596","4"],"15705":["US","15705","Indiana","Pennsylvania","PA","Indiana","063","","","40.6215","-79.1525","4"],"15710":["US","15710","Alverda","Pennsylvania","PA","Indiana","063","","","40.6303","-78.857","4"],"15712":["US","15712","Arcadia","Pennsylvania","PA","Indiana","063","","","40.7817","-78.8536","4"],"15713":["US","15713","Aultman","Pennsylvania","PA","Indiana","063","","","40.5698","-79.2617","4"],"15716":["US","15716","Black Lick","Pennsylvania","PA","Indiana","063","","","40.4725","-79.1869","4"],"15717":["US","15717","Blairsville","Pennsylvania","PA","Indiana","063","","","40.4413","-79.2533","4"],"15720":["US","15720","Brush Valley","Pennsylvania","PA","Indiana","063","","","40.5292","-79.0846","4"],"15723":["US","15723","Chambersville","Pennsylvania","PA","Indiana","063","","","40.7056","-79.1615","4"],"15724":["US","15724","Cherry Tree","Pennsylvania","PA","Indiana","063","","","40.7554","-78.8474","4"],"15725":["US","15725","Clarksburg","Pennsylvania","PA","Indiana","063","","","40.5039","-79.3677","4"],"15727":["US","15727","Clune","Pennsylvania","PA","Indiana","063","","","40.5503","-79.3237","1"],"15728":["US","15728","Clymer","Pennsylvania","PA","Indiana","063","","","40.6688","-79.0119","4"],"15729":["US","15729","Commodore","Pennsylvania","PA","Indiana","063","","","40.7016","-78.9134","4"],"15731":["US","15731","Coral","Pennsylvania","PA","Indiana","063","","","40.4992","-79.1739","4"],"15732":["US","15732","Creekside","Pennsylvania","PA","Indiana","063","","","40.7199","-79.2014","4"],"15734":["US","15734","Dixonville","Pennsylvania","PA","Indiana","063","","","40.7165","-79.007","4"],"15739":["US","15739","Ernest","Pennsylvania","PA","Indiana","063","","","40.678","-79.1657","4"],"15741":["US","15741","Gipsy","Pennsylvania","PA","Indiana","063","","","40.8073","-78.8764","4"],"15742":["US","15742","Glen Campbell","Pennsylvania","PA","Indiana","063","","","40.8508","-78.8555","4"],"15745":["US","15745","Heilwood","Pennsylvania","PA","Indiana","063","","","40.6207","-78.9186","4"],"15746":["US","15746","Hillsdale","Pennsylvania","PA","Indiana","063","","","40.7517","-78.885","4"],"15747":["US","15747","Home","Pennsylvania","PA","Indiana","063","","","40.7834","-79.1641","4"],"15748":["US","15748","Homer City","Pennsylvania","PA","Indiana","063","","","40.5245","-79.0843","4"],"15750":["US","15750","Josephine","Pennsylvania","PA","Indiana","063","","","40.4828","-79.185","4"],"15752":["US","15752","Kent","Pennsylvania","PA","Indiana","063","","","40.5412","-79.282","1"],"15754":["US","15754","Lucernemines","Pennsylvania","PA","Indiana","063","","","40.5567","-79.1515","1"],"15756":["US","15756","Mc Intyre","Pennsylvania","PA","Indiana","063","","","40.5684","-79.2999","1"],"15758":["US","15758","Marchand","Pennsylvania","PA","Indiana","063","","","40.8576","-79.0228","4"],"15759":["US","15759","Marion Center","Pennsylvania","PA","Indiana","063","","","40.7814","-79.0252","4"],"15761":["US","15761","Mentcle","Pennsylvania","PA","Indiana","063","","","40.6373","-78.8823","4"],"15763":["US","15763","Northpoint","Pennsylvania","PA","Indiana","063","","","40.9037","-79.1257","1"],"15765":["US","15765","Penn Run","Pennsylvania","PA","Indiana","063","","","40.6213","-78.9943","4"],"15771":["US","15771","Rochester Mills","Pennsylvania","PA","Indiana","063","","","40.8308","-78.9892","4"],"15772":["US","15772","Rossiter","Pennsylvania","PA","Indiana","063","","","40.8846","-78.9414","4"],"15777":["US","15777","Starford","Pennsylvania","PA","Indiana","063","","","40.7027","-78.9588","4"],"15783":["US","15783","West Lebanon","Pennsylvania","PA","Indiana","063","","","40.6026","-79.3537","4"],"15920":["US","15920","Armagh","Pennsylvania","PA","Indiana","063","","","40.4603","-79.0097","4"],"15929":["US","15929","Dilltown","Pennsylvania","PA","Indiana","063","","","40.4665","-79.0025","4"],"15949":["US","15949","Robinson","Pennsylvania","PA","Indiana","063","","","40.4042","-79.1395","4"],"15957":["US","15957","Strongstown","Pennsylvania","PA","Indiana","063","","","40.5727","-78.9","4"],"15711":["US","15711","Anita","Pennsylvania","PA","Jefferson","065","","","41.0018","-78.9666","4"],"15715":["US","15715","Big Run","Pennsylvania","PA","Jefferson","065","","","40.9704","-78.8758","4"],"15730":["US","15730","Coolspring","Pennsylvania","PA","Jefferson","065","","","41.0431","-79.0836","4"],"15733":["US","15733","De Lancey","Pennsylvania","PA","Jefferson","065","","","41.1411","-78.9629","1"],"15744":["US","15744","Hamilton","Pennsylvania","PA","Jefferson","065","","","40.9233","-79.0831","4"],"15764":["US","15764","Oliveburg","Pennsylvania","PA","Jefferson","065","","","40.9926","-79.0291","4"],"15767":["US","15767","Punxsutawney","Pennsylvania","PA","Jefferson","065","","","40.9479","-78.9681","4"],"15770":["US","15770","Ringgold","Pennsylvania","PA","Jefferson","065","","","40.9997","-79.1766","4"],"15776":["US","15776","Sprankle Mills","Pennsylvania","PA","Jefferson","065","","","41.0133","-79.114","4"],"15778":["US","15778","Timblin","Pennsylvania","PA","Jefferson","065","","","40.9684","-79.2014","4"],"15780":["US","15780","Valier","Pennsylvania","PA","Jefferson","065","","","40.9159","-79.0448","4"],"15781":["US","15781","Walston","Pennsylvania","PA","Jefferson","065","","","40.9651","-78.9948","4"],"15784":["US","15784","Worthville","Pennsylvania","PA","Jefferson","065","","","41.0238","-79.1387","4"],"15824":["US","15824","Brockway","Pennsylvania","PA","Jefferson","065","","","41.2406","-78.8116","4"],"15825":["US","15825","Brookville","Pennsylvania","PA","Jefferson","065","","","41.1627","-79.0816","4"],"15829":["US","15829","Corsica","Pennsylvania","PA","Jefferson","065","","","41.1762","-79.1976","4"],"15840":["US","15840","Falls Creek","Pennsylvania","PA","Jefferson","065","","","41.1455","-78.8128","4"],"15847":["US","15847","Knox Dale","Pennsylvania","PA","Jefferson","065","","","41.0862","-79.0264","4"],"15851":["US","15851","Reynoldsville","Pennsylvania","PA","Jefferson","065","","","41.097","-78.8886","4"],"15860":["US","15860","Sigel","Pennsylvania","PA","Jefferson","065","","","41.3099","-79.054","4"],"15863":["US","15863","Stump Creek","Pennsylvania","PA","Jefferson","065","","","41.0126","-78.8373","4"],"15864":["US","15864","Summerville","Pennsylvania","PA","Jefferson","065","","","41.1058","-79.1726","4"],"15865":["US","15865","Sykesville","Pennsylvania","PA","Jefferson","065","","","41.0514","-78.8195","4"],"15411":["US","15411","Addison","Pennsylvania","PA","Somerset","111","","","39.7476","-79.3454","4"],"15424":["US","15424","Confluence","Pennsylvania","PA","Somerset","111","","","39.8129","-79.3567","4"],"15485":["US","15485","Ursina","Pennsylvania","PA","Somerset","111","","","39.8173","-79.3306","4"],"15501":["US","15501","Somerset","Pennsylvania","PA","Somerset","111","","","40.0248","-79.0808","4"],"15502":["US","15502","Hidden Valley","Pennsylvania","PA","Somerset","111","","","40.046","-79.2585","1"],"15510":["US","15510","Somerset","Pennsylvania","PA","Somerset","111","","","39.9633","-79.0409","4"],"15520":["US","15520","Acosta","Pennsylvania","PA","Somerset","111","","","40.1104","-79.0689","4"],"15530":["US","15530","Berlin","Pennsylvania","PA","Somerset","111","","","39.9188","-78.9637","4"],"15531":["US","15531","Boswell","Pennsylvania","PA","Somerset","111","","","40.1918","-79.0362","4"],"15532":["US","15532","Boynton","Pennsylvania","PA","Somerset","111","","","39.7673","-79.062","4"],"15538":["US","15538","Fairhope","Pennsylvania","PA","Somerset","111","","","39.868","-78.8362","4"],"15540":["US","15540","Fort Hill","Pennsylvania","PA","Somerset","111","","","39.7961","-79.2472","4"],"15541":["US","15541","Friedens","Pennsylvania","PA","Somerset","111","","","40.011","-78.9033","4"],"15542":["US","15542","Garrett","Pennsylvania","PA","Somerset","111","","","39.8646","-79.0616","4"],"15544":["US","15544","Gray","Pennsylvania","PA","Somerset","111","","","40.1377","-79.0926","4"],"15546":["US","15546","Jenners","Pennsylvania","PA","Somerset","111","","","40.1431","-79.0428","4"],"15547":["US","15547","Jennerstown","Pennsylvania","PA","Somerset","111","","","40.1595","-79.0616","4"],"15548":["US","15548","Kantner","Pennsylvania","PA","Somerset","111","","","40.1011","-78.9387","4"],"15549":["US","15549","Listie","Pennsylvania","PA","Somerset","111","","","40.0208","-79.0123","4"],"15551":["US","15551","Markleton","Pennsylvania","PA","Somerset","111","","","39.8691","-79.2879","4"],"15552":["US","15552","Meyersdale","Pennsylvania","PA","Somerset","111","","","39.7905","-79.0261","4"],"15553":["US","15553","New Baltimore","Pennsylvania","PA","Somerset","111","","","39.9828","-78.7719","4"],"15555":["US","15555","Quecreek","Pennsylvania","PA","Somerset","111","","","40.0914","-79.0872","4"],"15557":["US","15557","Rockwood","Pennsylvania","PA","Somerset","111","","","39.9373","-79.1865","4"],"15558":["US","15558","Salisbury","Pennsylvania","PA","Somerset","111","","","39.7531","-79.0835","4"],"15560":["US","15560","Shanksville","Pennsylvania","PA","Somerset","111","","","40.0171","-78.9077","4"],"15561":["US","15561","Sipesville","Pennsylvania","PA","Somerset","111","","","40.0964","-79.0902","4"],"15562":["US","15562","Springs","Pennsylvania","PA","Somerset","111","","","39.748","-79.1237","4"],"15563":["US","15563","Stoystown","Pennsylvania","PA","Somerset","111","","","40.0948","-78.9658","4"],"15564":["US","15564","Wellersburg","Pennsylvania","PA","Somerset","111","","","39.7299","-78.8441","4"],"15565":["US","15565","West Salisbury","Pennsylvania","PA","Somerset","111","","","39.7542","-79.095","4"],"15924":["US","15924","Cairnbrook","Pennsylvania","PA","Somerset","111","","","40.1149","-78.7851","4"],"15926":["US","15926","Central City","Pennsylvania","PA","Somerset","111","","","40.0913","-78.8448","4"],"15928":["US","15928","Davidsville","Pennsylvania","PA","Somerset","111","","","40.2245","-78.9363","4"],"15935":["US","15935","Hollsopple","Pennsylvania","PA","Somerset","111","","","40.2343","-78.9515","4"],"15936":["US","15936","Hooversville","Pennsylvania","PA","Somerset","111","","","40.1488","-78.9141","4"],"15937":["US","15937","Jerome","Pennsylvania","PA","Somerset","111","","","40.2084","-78.9873","4"],"15953":["US","15953","Seanor","Pennsylvania","PA","Somerset","111","","","40.212","-78.8984","4"],"15959":["US","15959","Tire Hill","Pennsylvania","PA","Somerset","111","","","40.268","-78.9156","4"],"15963":["US","15963","Windber","Pennsylvania","PA","Somerset","111","","","40.2287","-78.8303","4"],"15004":["US","15004","Atlasburg","Pennsylvania","PA","Washington","125","","","40.3413","-80.3822","4"],"15019":["US","15019","Bulger","Pennsylvania","PA","Washington","125","","","40.4051","-80.3622","4"],"15021":["US","15021","Burgettstown","Pennsylvania","PA","Washington","125","","","40.3821","-80.4044","4"],"15022":["US","15022","Charleroi","Pennsylvania","PA","Washington","125","","","40.1404","-79.92","4"],"15033":["US","15033","Donora","Pennsylvania","PA","Washington","125","","","40.1768","-79.8619","4"],"15038":["US","15038","Elrama","Pennsylvania","PA","Washington","125","","","40.2521","-79.9252","4"],"15053":["US","15053","Joffre","Pennsylvania","PA","Washington","125","","","40.38","-80.3605","4"],"15054":["US","15054","Langeloth","Pennsylvania","PA","Washington","125","","","40.3625","-80.4086","4"],"15055":["US","15055","Lawrence","Pennsylvania","PA","Washington","125","","","40.3058","-80.1219","4"],"15057":["US","15057","Mc Donald","Pennsylvania","PA","Washington","125","","","40.3697","-80.2562","1"],"15060":["US","15060","Midway","Pennsylvania","PA","Washington","125","","","40.368","-80.2921","4"],"15063":["US","15063","Monongahela","Pennsylvania","PA","Washington","125","","","40.1937","-79.9241","4"],"15067":["US","15067","New Eagle","Pennsylvania","PA","Washington","125","","","40.2066","-79.9534","4"],"15078":["US","15078","Slovan","Pennsylvania","PA","Washington","125","","","40.3584","-80.3879","4"],"15301":["US","15301","Washington","Pennsylvania","PA","Washington","125","","","40.1717","-80.256","4"],"15311":["US","15311","Amity","Pennsylvania","PA","Washington","125","","","40.0498","-80.1681","4"],"15312":["US","15312","Avella","Pennsylvania","PA","Washington","125","","","40.2734","-80.4565","4"],"15313":["US","15313","Beallsville","Pennsylvania","PA","Washington","125","","","40.0655","-80.0221","4"],"15314":["US","15314","Bentleyville","Pennsylvania","PA","Washington","125","","","40.1187","-80.007","4"],"15317":["US","15317","Canonsburg","Pennsylvania","PA","Washington","125","","","40.2706","-80.1668","4"],"15321":["US","15321","Cecil","Pennsylvania","PA","Washington","125","","","40.3234","-80.1879","4"],"15323":["US","15323","Claysville","Pennsylvania","PA","Washington","125","","","40.1179","-80.4103","4"],"15324":["US","15324","Cokeburg","Pennsylvania","PA","Washington","125","","","40.1008","-80.0652","4"],"15329":["US","15329","Prosperity","Pennsylvania","PA","Washington","125","","","40.0224","-80.2613","4"],"15330":["US","15330","Eighty Four","Pennsylvania","PA","Washington","125","","","40.1868","-80.0627","4"],"15331":["US","15331","Ellsworth","Pennsylvania","PA","Washington","125","","","40.1073","-80.0204","4"],"15332":["US","15332","Finleyville","Pennsylvania","PA","Washington","125","","","40.2593","-79.9753","4"],"15333":["US","15333","Fredericktown","Pennsylvania","PA","Washington","125","","","40.0026","-79.9981","4"],"15336":["US","15336","Gastonville","Pennsylvania","PA","Washington","125","","","40.2601","-79.9927","4"],"15339":["US","15339","Hendersonville","Pennsylvania","PA","Washington","125","","","40.3018","-80.1543","4"],"15340":["US","15340","Hickory","Pennsylvania","PA","Washington","125","","","40.2925","-80.3025","4"],"15342":["US","15342","Houston","Pennsylvania","PA","Washington","125","","","40.2425","-80.2209","4"],"15345":["US","15345","Marianna","Pennsylvania","PA","Washington","125","","","40.0331","-80.1145","4"],"15347":["US","15347","Meadow Lands","Pennsylvania","PA","Washington","125","","","40.2174","-80.2269","4"],"15348":["US","15348","Millsboro","Pennsylvania","PA","Washington","125","","","39.9867","-79.9937","4"],"15350":["US","15350","Muse","Pennsylvania","PA","Washington","125","","","40.2928","-80.2003","4"],"15358":["US","15358","Richeyville","Pennsylvania","PA","Washington","125","","","40.0563","-79.9926","4"],"15360":["US","15360","Scenery Hill","Pennsylvania","PA","Washington","125","","","40.0859","-80.0703","4"],"15361":["US","15361","Southview","Pennsylvania","PA","Washington","125","","","40.3282","-80.2563","4"],"15363":["US","15363","Strabane","Pennsylvania","PA","Washington","125","","","40.2505","-80.1984","4"],"15365":["US","15365","Taylorstown","Pennsylvania","PA","Washington","125","","","40.1611","-80.3781","4"],"15366":["US","15366","Van Voorhis","Pennsylvania","PA","Washington","125","","","40.1562","-79.9742","4"],"15367":["US","15367","Venetia","Pennsylvania","PA","Washington","125","","","40.2755","-80.0598","4"],"15368":["US","15368","Vestaburg","Pennsylvania","PA","Washington","125","","","40.0144","-79.9889","4"],"15376":["US","15376","West Alexander","Pennsylvania","PA","Washington","125","","","40.1065","-80.4978","4"],"15377":["US","15377","West Finley","Pennsylvania","PA","Washington","125","","","39.9914","-80.4408","4"],"15378":["US","15378","Westland","Pennsylvania","PA","Washington","125","","","40.2775","-80.2731","4"],"15379":["US","15379","West Middletown","Pennsylvania","PA","Washington","125","","","40.2417","-80.4242","4"],"15412":["US","15412","Allenport","Pennsylvania","PA","Washington","125","","","40.0959","-79.8499","4"],"15419":["US","15419","California","Pennsylvania","PA","Washington","125","","","40.0625","-79.8953","4"],"15423":["US","15423","Coal Center","Pennsylvania","PA","Washington","125","","","40.0973","-79.8839","4"],"15427":["US","15427","Daisytown","Pennsylvania","PA","Washington","125","","","40.0743","-79.967","4"],"15429":["US","15429","Denbo","Pennsylvania","PA","Washington","125","","","40.0081","-79.9392","4"],"15432":["US","15432","Dunlevy","Pennsylvania","PA","Washington","125","","","40.1151","-79.8627","4"],"15434":["US","15434","Elco","Pennsylvania","PA","Washington","125","","","40.0797","-79.8758","4"],"15477":["US","15477","Roscoe","Pennsylvania","PA","Washington","125","","","40.0787","-79.8656","4"],"15483":["US","15483","Stockdale","Pennsylvania","PA","Washington","125","","","40.0826","-79.8501","4"],"15062":["US","15062","Monessen","Pennsylvania","PA","Westmoreland","129","","","40.1524","-79.8835","4"],"15068":["US","15068","New Kensington","Pennsylvania","PA","Westmoreland","129","","","40.5616","-79.7129","4"],"15069":["US","15069","New Kensington","Pennsylvania","PA","Westmoreland","129","","","40.5698","-79.7648","4"],"15072":["US","15072","Pricedale","Pennsylvania","PA","Westmoreland","129","","","40.1393","-79.8562","4"],"15083":["US","15083","Sutersville","Pennsylvania","PA","Westmoreland","129","","","40.2382","-79.7922","4"],"15085":["US","15085","Trafford","Pennsylvania","PA","Westmoreland","129","","","40.3857","-79.7223","4"],"15087":["US","15087","Webster","Pennsylvania","PA","Westmoreland","129","","","40.1851","-79.8487","4"],"15089":["US","15089","West Newton","Pennsylvania","PA","Westmoreland","129","","","40.2075","-79.758","4"],"15448":["US","15448","Jacobs Creek","Pennsylvania","PA","Westmoreland","129","","","40.1331","-79.7417","4"],"15479":["US","15479","Smithton","Pennsylvania","PA","Westmoreland","129","","","40.1553","-79.7381","4"],"15601":["US","15601","Greensburg","Pennsylvania","PA","Westmoreland","129","","","40.3074","-79.5424","4"],"15605":["US","15605","Greensburg","Pennsylvania","PA","Westmoreland","129","","","40.3602","-79.4398","4"],"15606":["US","15606","Greensburg","Pennsylvania","PA","Westmoreland","129","","","40.3015","-79.5389","4"],"15610":["US","15610","Acme","Pennsylvania","PA","Westmoreland","129","","","40.1201","-79.4051","4"],"15611":["US","15611","Adamsburg","Pennsylvania","PA","Westmoreland","129","","","40.3126","-79.6565","4"],"15612":["US","15612","Alverton","Pennsylvania","PA","Westmoreland","129","","","40.1373","-79.5997","4"],"15613":["US","15613","Apollo","Pennsylvania","PA","Westmoreland","129","","","40.5565","-79.5772","4"],"15615":["US","15615","Ardara","Pennsylvania","PA","Westmoreland","129","","","40.3578","-79.735","4"],"15616":["US","15616","Armbrust","Pennsylvania","PA","Westmoreland","129","","","40.2237","-79.5512","4"],"15617":["US","15617","Arona","Pennsylvania","PA","Westmoreland","129","","","40.268","-79.6591","4"],"15618":["US","15618","Avonmore","Pennsylvania","PA","Westmoreland","129","","","40.5221","-79.4853","4"],"15619":["US","15619","Bovard","Pennsylvania","PA","Westmoreland","129","","","40.3198","-79.5034","4"],"15620":["US","15620","Bradenville","Pennsylvania","PA","Westmoreland","129","","","40.3238","-79.3434","4"],"15621":["US","15621","Calumet","Pennsylvania","PA","Westmoreland","129","","","40.2109","-79.4853","4"],"15622":["US","15622","Champion","Pennsylvania","PA","Westmoreland","129","","","40.044","-79.3247","4"],"15623":["US","15623","Claridge","Pennsylvania","PA","Westmoreland","129","","","40.3692","-79.619","4"],"15624":["US","15624","Crabtree","Pennsylvania","PA","Westmoreland","129","","","40.3623","-79.4706","4"],"15625":["US","15625","Darragh","Pennsylvania","PA","Westmoreland","129","","","40.2665","-79.6787","4"],"15626":["US","15626","Delmont","Pennsylvania","PA","Westmoreland","129","","","40.4139","-79.5764","4"],"15627":["US","15627","Derry","Pennsylvania","PA","Westmoreland","129","","","40.3349","-79.3326","4"],"15628":["US","15628","Donegal","Pennsylvania","PA","Westmoreland","129","","","40.0996","-79.381","4"],"15629":["US","15629","East Vandergrift","Pennsylvania","PA","Westmoreland","129","","","40.598","-79.5624","4"],"15632":["US","15632","Export","Pennsylvania","PA","Westmoreland","129","","","40.4252","-79.611","4"],"15633":["US","15633","Forbes Road","Pennsylvania","PA","Westmoreland","129","","","40.354","-79.5217","4"],"15634":["US","15634","Grapeville","Pennsylvania","PA","Westmoreland","129","","","40.3239","-79.6049","4"],"15635":["US","15635","Hannastown","Pennsylvania","PA","Westmoreland","129","","","40.352","-79.4979","4"],"15636":["US","15636","Harrison City","Pennsylvania","PA","Westmoreland","129","","","40.366","-79.6565","4"],"15637":["US","15637","Herminie","Pennsylvania","PA","Westmoreland","129","","","40.2455","-79.7172","4"],"15638":["US","15638","Hostetter","Pennsylvania","PA","Westmoreland","129","","","40.2662","-79.3984","4"],"15639":["US","15639","Hunker","Pennsylvania","PA","Westmoreland","129","","","40.2149","-79.5824","4"],"15640":["US","15640","Hutchinson","Pennsylvania","PA","Westmoreland","129","","","40.2251","-79.7328","4"],"15641":["US","15641","Hyde Park","Pennsylvania","PA","Westmoreland","129","","","40.6311","-79.5899","4"],"15642":["US","15642","Irwin","Pennsylvania","PA","Westmoreland","129","","","40.3191","-79.7205","4"],"15644":["US","15644","Jeannette","Pennsylvania","PA","Westmoreland","129","","","40.3295","-79.6144","4"],"15646":["US","15646","Jones Mills","Pennsylvania","PA","Westmoreland","129","","","40.0889","-79.3427","4"],"15647":["US","15647","Larimer","Pennsylvania","PA","Westmoreland","129","","","40.3453","-79.7264","4"],"15650":["US","15650","Latrobe","Pennsylvania","PA","Westmoreland","129","","","40.2926","-79.4103","4"],"15655":["US","15655","Laughlintown","Pennsylvania","PA","Westmoreland","129","","","40.212","-79.1978","4"],"15658":["US","15658","Ligonier","Pennsylvania","PA","Westmoreland","129","","","40.2431","-79.2375","4"],"15660":["US","15660","Lowber","Pennsylvania","PA","Westmoreland","129","","","40.2459","-79.7709","4"],"15661":["US","15661","Loyalhanna","Pennsylvania","PA","Westmoreland","129","","","40.3222","-79.3601","4"],"15662":["US","15662","Luxor","Pennsylvania","PA","Westmoreland","129","","","40.3342","-79.4781","4"],"15663":["US","15663","Madison","Pennsylvania","PA","Westmoreland","129","","","40.2467","-79.676","4"],"15664":["US","15664","Mammoth","Pennsylvania","PA","Westmoreland","129","","","40.3108","-79.6172","4"],"15665":["US","15665","Manor","Pennsylvania","PA","Westmoreland","129","","","40.334","-79.67","4"],"15666":["US","15666","Mount Pleasant","Pennsylvania","PA","Westmoreland","129","","","40.1742","-79.5134","4"],"15668":["US","15668","Murrysville","Pennsylvania","PA","Westmoreland","129","","","40.4467","-79.6842","4"],"15670":["US","15670","New Alexandria","Pennsylvania","PA","Westmoreland","129","","","40.3987","-79.422","4"],"15671":["US","15671","New Derry","Pennsylvania","PA","Westmoreland","129","","","40.3494","-79.3225","4"],"15672":["US","15672","New Stanton","Pennsylvania","PA","Westmoreland","129","","","40.2192","-79.6095","4"],"15674":["US","15674","Norvelt","Pennsylvania","PA","Westmoreland","129","","","40.216","-79.4872","4"],"15675":["US","15675","Penn","Pennsylvania","PA","Westmoreland","129","","","40.3301","-79.6413","4"],"15676":["US","15676","Pleasant Unity","Pennsylvania","PA","Westmoreland","129","","","40.2424","-79.4542","4"],"15677":["US","15677","Rector","Pennsylvania","PA","Westmoreland","129","","","40.1864","-79.2473","4"],"15678":["US","15678","Rillton","Pennsylvania","PA","Westmoreland","129","","","40.2872","-79.7262","4"],"15679":["US","15679","Ruffs Dale","Pennsylvania","PA","Westmoreland","129","","","40.1585","-79.6277","4"],"15680":["US","15680","Salina","Pennsylvania","PA","Westmoreland","129","","","40.5189","-79.4959","4"],"15683":["US","15683","Scottdale","Pennsylvania","PA","Westmoreland","129","","","40.1029","-79.593","4"],"15684":["US","15684","Slickville","Pennsylvania","PA","Westmoreland","129","","","40.4653","-79.5067","4"],"15685":["US","15685","Southwest","Pennsylvania","PA","Westmoreland","129","","","40.3602","-79.4398","4"],"15687":["US","15687","Stahlstown","Pennsylvania","PA","Westmoreland","129","","","40.1386","-79.3445","4"],"15688":["US","15688","Tarrs","Pennsylvania","PA","Westmoreland","129","","","40.1686","-79.5848","4"],"15689":["US","15689","United","Pennsylvania","PA","Westmoreland","129","","","40.2184","-79.4878","4"],"15690":["US","15690","Vandergrift","Pennsylvania","PA","Westmoreland","129","","","40.6418","-79.5399","4"],"15691":["US","15691","Wendel","Pennsylvania","PA","Westmoreland","129","","","40.294","-79.6866","4"],"15692":["US","15692","Westmoreland City","Pennsylvania","PA","Westmoreland","129","","","40.3294","-79.6806","4"],"15693":["US","15693","Whitney","Pennsylvania","PA","Westmoreland","129","","","40.2534","-79.4103","4"],"15695":["US","15695","Wyano","Pennsylvania","PA","Westmoreland","129","","","40.1962","-79.6942","4"],"15696":["US","15696","Youngstown","Pennsylvania","PA","Westmoreland","129","","","40.2793","-79.3661","4"],"15697":["US","15697","Youngwood","Pennsylvania","PA","Westmoreland","129","","","40.2395","-79.5823","4"],"15698":["US","15698","Yukon","Pennsylvania","PA","Westmoreland","129","","","40.2155","-79.6849","4"],"15779":["US","15779","Torrance","Pennsylvania","PA","Westmoreland","129","","","40.3992","-79.2177","4"],"15923":["US","15923","Bolivar","Pennsylvania","PA","Westmoreland","129","","","40.3673","-79.1605","4"],"15944":["US","15944","New Florence","Pennsylvania","PA","Westmoreland","129","","","40.3823","-79.0968","4"],"15954":["US","15954","Seward","Pennsylvania","PA","Westmoreland","129","","","40.4099","-79.0232","4"]}