{"70516":["US","70516","Branch","Louisiana","LA","Acadia","001","","","30.3446","-92.3459","4"],"70525":["US","70525","Church Point","Louisiana","LA","Acadia","001","","","30.4013","-92.224","4"],"70526":["US","70526","Crowley","Louisiana","LA","Acadia","001","","","30.2148","-92.3777","4"],"70527":["US","70527","Crowley","Louisiana","LA","Acadia","001","","","30.2284","-92.3018","4"],"70531":["US","70531","Egan","Louisiana","LA","Acadia","001","","","30.251","-92.5002","4"],"70534":["US","70534","Estherwood","Louisiana","LA","Acadia","001","","","30.1808","-92.4643","4"],"70537":["US","70537","Evangeline","Louisiana","LA","Acadia","001","","","30.2683","-92.5532","4"],"70543":["US","70543","Iota","Louisiana","LA","Acadia","001","","","30.3313","-92.4957","4"],"70556":["US","70556","Mermentau","Louisiana","LA","Acadia","001","","","30.1861","-92.5722","4"],"70559":["US","70559","Morse","Louisiana","LA","Acadia","001","","","30.1298","-92.4767","4"],"70578":["US","70578","Rayne","Louisiana","LA","Acadia","001","","","30.2349","-92.2685","4"],"70638":["US","70638","Elizabeth","Louisiana","LA","Allen","003","","","30.8547","-92.7815","4"],"70644":["US","70644","Grant","Louisiana","LA","Allen","003","","","30.7962","-92.9517","4"],"70648":["US","70648","Kinder","Louisiana","LA","Allen","003","","","30.4607","-92.8693","4"],"70651":["US","70651","Leblanc","Louisiana","LA","Allen","003","","","30.5648","-92.9583","1"],"70654":["US","70654","Mittie","Louisiana","LA","Allen","003","","","30.7144","-92.9068","4"],"70655":["US","70655","Oberlin","Louisiana","LA","Allen","003","","","30.6162","-92.7527","4"],"70658":["US","70658","Reeves","Louisiana","LA","Allen","003","","","30.521","-93.0477","4"],"70346":["US","70346","Donaldsonville","Louisiana","LA","Ascension","005","","","30.1018","-90.997","4"],"70707":["US","70707","Gonzales","Louisiana","LA","Ascension","005","","","30.2047","-90.8695","4"],"70718":["US","70718","Brittany","Louisiana","LA","Ascension","005","","","30.201","-90.8689","4"],"70725":["US","70725","Darrow","Louisiana","LA","Ascension","005","","","30.13","-90.9651","4"],"70728":["US","70728","Duplessis","Louisiana","LA","Ascension","005","","","30.2954","-90.9458","4"],"70734":["US","70734","Geismar","Louisiana","LA","Ascension","005","","","30.2196","-91.0079","4"],"70737":["US","70737","Gonzales","Louisiana","LA","Ascension","005","","","30.2473","-90.918","4"],"70738":["US","70738","Burnside","Louisiana","LA","Ascension","005","","","30.1388","-90.924","4"],"70769":["US","70769","Prairieville","Louisiana","LA","Ascension","005","","","30.3073","-90.9405","4"],"70774":["US","70774","Saint Amant","Louisiana","LA","Ascension","005","","","30.2385","-90.8435","4"],"70778":["US","70778","Sorrento","Louisiana","LA","Ascension","005","","","30.1854","-90.8631","4"],"70339":["US","70339","Pierre Part","Louisiana","LA","Assumption","007","","","29.9476","-91.1885","4"],"70341":["US","70341","Belle Rose","Louisiana","LA","Assumption","007","","","30.026","-91.0444","4"],"70372":["US","70372","Labadieville","Louisiana","LA","Assumption","007","","","29.8345","-90.9613","4"],"70390":["US","70390","Napoleonville","Louisiana","LA","Assumption","007","","","29.9288","-91.0266","4"],"70391":["US","70391","Paincourtville","Louisiana","LA","Assumption","007","","","29.9902","-91.0588","4"],"70393":["US","70393","Plattenville","Louisiana","LA","Assumption","007","","","29.9974","-91.0232","4"],"70634":["US","70634","Deridder","Louisiana","LA","Beauregard","011","","","30.8287","-93.2685","4"],"70637":["US","70637","Dry Creek","Louisiana","LA","Beauregard","011","","","30.6859","-92.9843","4"],"70652":["US","70652","Longville","Louisiana","LA","Beauregard","011","","","30.58","-93.2548","4"],"70653":["US","70653","Merryville","Louisiana","LA","Beauregard","011","","","30.6716","-93.5613","4"],"70657":["US","70657","Ragley","Louisiana","LA","Beauregard","011","","","30.4703","-93.2337","4"],"70660":["US","70660","Singer","Louisiana","LA","Beauregard","011","","","30.5329","-93.465","4"],"70662":["US","70662","Sugartown","Louisiana","LA","Beauregard","011","","","30.8277","-93.017","4"],"70601":["US","70601","Lake Charles","Louisiana","LA","Calcasieu","019","","","30.2285","-93.188","4"],"70602":["US","70602","Lake Charles","Louisiana","LA","Calcasieu","019","","","30.2642","-93.3265","4"],"70605":["US","70605","Lake Charles","Louisiana","LA","Calcasieu","019","","","30.1693","-93.2218","4"],"70606":["US","70606","Lake Charles","Louisiana","LA","Calcasieu","019","","","30.2642","-93.3265","4"],"70607":["US","70607","Lake Charles","Louisiana","LA","Calcasieu","019","","","30.1244","-93.1835","4"],"70609":["US","70609","Lake Charles","Louisiana","LA","Calcasieu","019","","","30.2642","-93.3265","4"],"70611":["US","70611","Lake Charles","Louisiana","LA","Calcasieu","019","","","30.322","-93.2111","4"],"70612":["US","70612","Lake Charles","Louisiana","LA","Calcasieu","019","","","30.2642","-93.3265","4"],"70615":["US","70615","Lake Charles","Louisiana","LA","Calcasieu","019","","","30.2585","-93.1146","4"],"70616":["US","70616","Lake Charles","Louisiana","LA","Calcasieu","019","","","30.2642","-93.3265","4"],"70629":["US","70629","Lake Charles","Louisiana","LA","Calcasieu","019","","","30.2642","-93.3265","4"],"70630":["US","70630","Bell City","Louisiana","LA","Calcasieu","019","","","30.1054","-93.0372","4"],"70633":["US","70633","Dequincy","Louisiana","LA","Calcasieu","019","","","30.4211","-93.4151","4"],"70646":["US","70646","Hayes","Louisiana","LA","Calcasieu","019","","","30.097","-92.9146","4"],"70647":["US","70647","Iowa","Louisiana","LA","Calcasieu","019","","","30.2219","-93.0259","4"],"70661":["US","70661","Starks","Louisiana","LA","Calcasieu","019","","","30.3085","-93.6615","4"],"70663":["US","70663","Sulphur","Louisiana","LA","Calcasieu","019","","","30.219","-93.3639","4"],"70664":["US","70664","Sulphur","Louisiana","LA","Calcasieu","019","","","30.2642","-93.3265","4"],"70665":["US","70665","Sulphur","Louisiana","LA","Calcasieu","019","","","30.2009","-93.4437","4"],"70668":["US","70668","Vinton","Louisiana","LA","Calcasieu","019","","","30.2015","-93.5728","4"],"70669":["US","70669","Westlake","Louisiana","LA","Calcasieu","019","","","30.2613","-93.2688","4"],"70631":["US","70631","Cameron","Louisiana","LA","Cameron","023","","","29.7911","-93.438","4"],"70632":["US","70632","Creole","Louisiana","LA","Cameron","023","","","29.8646","-93.0033","4"],"70643":["US","70643","Grand Chenier","Louisiana","LA","Cameron","023","","","29.7644","-92.9261","4"],"70645":["US","70645","Hackberry","Louisiana","LA","Cameron","023","","","29.9822","-93.375","4"],"70704":["US","70704","Baker","Louisiana","LA","East Baton Rouge Parish","033","","","30.5159","-91.0804","4"],"70714":["US","70714","Baker","Louisiana","LA","East Baton Rouge Parish","033","","","30.5814","-91.1429","4"],"70739":["US","70739","Greenwell Springs","Louisiana","LA","East Baton Rouge Parish","033","","","30.5984","-90.9705","4"],"70770":["US","70770","Pride","Louisiana","LA","East Baton Rouge Parish","033","","","30.6133","-90.9943","4"],"70791":["US","70791","Zachary","Louisiana","LA","East Baton Rouge Parish","033","","","30.6561","-91.1358","4"],"70801":["US","70801","Baton Rouge","Louisiana","LA","East Baton Rouge Parish","033","","","30.4492","-91.1856","4"],"70802":["US","70802","Baton Rouge","Louisiana","LA","East Baton Rouge Parish","033","","","30.4438","-91.1775","4"],"70803":["US","70803","Baton Rouge","Louisiana","LA","East Baton Rouge Parish","033","","","30.405","-91.1868","4"],"70804":["US","70804","Baton Rouge","Louisiana","LA","East Baton Rouge Parish","033","","","30.3863","-91.1339","4"],"70805":["US","70805","Baton Rouge","Louisiana","LA","East Baton Rouge Parish","033","","","30.486","-91.1481","4"],"70806":["US","70806","Baton Rouge","Louisiana","LA","East Baton Rouge Parish","033","","","30.4485","-91.13","4"],"70807":["US","70807","Baton Rouge","Louisiana","LA","East Baton Rouge Parish","033","","","30.5768","-91.2246","4"],"70808":["US","70808","Baton Rouge","Louisiana","LA","East Baton Rouge Parish","033","","","30.4066","-91.1468","4"],"70809":["US","70809","Baton Rouge","Louisiana","LA","East Baton Rouge Parish","033","","","30.4089","-91.0842","4"],"70810":["US","70810","Baton Rouge","Louisiana","LA","East Baton Rouge Parish","033","","","30.3633","-91.0919","4"],"70811":["US","70811","Baton Rouge","Louisiana","LA","East Baton Rouge Parish","033","","","30.5317","-91.1167","4"],"70812":["US","70812","Baton Rouge","Louisiana","LA","East Baton Rouge Parish","033","","","30.5052","-91.1181","4"],"70813":["US","70813","Baton Rouge","Louisiana","LA","East Baton Rouge Parish","033","","","30.5201","-91.1949","4"],"70814":["US","70814","Baton Rouge","Louisiana","LA","East Baton Rouge Parish","033","","","30.4848","-91.0689","4"],"70815":["US","70815","Baton Rouge","Louisiana","LA","East Baton Rouge Parish","033","","","30.4558","-91.0596","4"],"70816":["US","70816","Baton Rouge","Louisiana","LA","East Baton Rouge Parish","033","","","30.4273","-91.0356","4"],"70817":["US","70817","Baton Rouge","Louisiana","LA","East Baton Rouge Parish","033","","","30.3904","-91.0021","4"],"70818":["US","70818","Baton Rouge","Louisiana","LA","East Baton Rouge Parish","033","","","30.5408","-91.05","4"],"70819":["US","70819","Baton Rouge","Louisiana","LA","East Baton Rouge Parish","033","","","30.4668","-91.0156","4"],"70820":["US","70820","Baton Rouge","Louisiana","LA","East Baton Rouge Parish","033","","","30.3795","-91.1671","4"],"70821":["US","70821","Baton Rouge","Louisiana","LA","East Baton Rouge Parish","033","","","30.4613","-91.0447","4"],"70822":["US","70822","Baton Rouge","Louisiana","LA","East Baton Rouge Parish","033","","","30.5159","-91.0804","4"],"70823":["US","70823","Baton Rouge","Louisiana","LA","East Baton Rouge Parish","033","","","30.5159","-91.0804","4"],"70825":["US","70825","Baton Rouge","Louisiana","LA","East Baton Rouge Parish","033","","","30.5159","-91.0804","4"],"70826":["US","70826","Baton Rouge","Louisiana","LA","East Baton Rouge Parish","033","","","30.5159","-91.0804","4"],"70827":["US","70827","Baton Rouge","Louisiana","LA","East Baton Rouge Parish","033","","","30.4338","-91.0825","4"],"70831":["US","70831","Baton Rouge","Louisiana","LA","East Baton Rouge Parish","033","","","30.5159","-91.0804","4"],"70833":["US","70833","Baton Rouge","Louisiana","LA","East Baton Rouge Parish","033","","","30.5159","-91.0804","4"],"70835":["US","70835","Baton Rouge","Louisiana","LA","East Baton Rouge Parish","033","","","30.5159","-91.0804","4"],"70836":["US","70836","Baton Rouge","Louisiana","LA","East Baton Rouge Parish","033","","","30.392","-91.0892","4"],"70837":["US","70837","Baton Rouge","Louisiana","LA","East Baton Rouge Parish","033","","","30.5159","-91.0804","4"],"70873":["US","70873","Baton Rouge","Louisiana","LA","East Baton Rouge Parish","033","","","30.5305","-91.1163","4"],"70874":["US","70874","Baton Rouge","Louisiana","LA","East Baton Rouge Parish","033","","","30.5902","-91.2054","4"],"70879":["US","70879","Baton Rouge","Louisiana","LA","East Baton Rouge Parish","033","","","30.5159","-91.0804","4"],"70884":["US","70884","Baton Rouge","Louisiana","LA","East Baton Rouge Parish","033","","","30.5159","-91.0804","4"],"70891":["US","70891","Baton Rouge","Louisiana","LA","East Baton Rouge Parish","033","","","30.4492","-91.1547","4"],"70892":["US","70892","Baton Rouge","Louisiana","LA","East Baton Rouge Parish","033","","","30.4507","-91.1546","4"],"70893":["US","70893","Baton Rouge","Louisiana","LA","East Baton Rouge Parish","033","","","30.413","-91.1715","4"],"70894":["US","70894","Baton Rouge","Louisiana","LA","East Baton Rouge Parish","033","","","30.5159","-91.0804","4"],"70895":["US","70895","Baton Rouge","Louisiana","LA","East Baton Rouge Parish","033","","","30.5159","-91.0804","4"],"70896":["US","70896","Baton Rouge","Louisiana","LA","East Baton Rouge Parish","033","","","30.5159","-91.0804","4"],"70898":["US","70898","Baton Rouge","Louisiana","LA","East Baton Rouge Parish","033","","","30.5159","-91.0804","4"],"70722":["US","70722","Clinton","Louisiana","LA","East Feliciana","037","","","30.8249","-90.9331","4"],"70730":["US","70730","Ethel","Louisiana","LA","East Feliciana","037","","","30.8131","-91.11","4"],"70748":["US","70748","Jackson","Louisiana","LA","East Feliciana","037","","","30.8087","-91.1987","4"],"70761":["US","70761","Norwood","Louisiana","LA","East Feliciana","037","","","30.9518","-91.0629","4"],"70777":["US","70777","Slaughter","Louisiana","LA","East Feliciana","037","","","30.7383","-91.07","4"],"70789":["US","70789","Wilson","Louisiana","LA","East Feliciana","037","","","30.9473","-91.0655","4"],"70515":["US","70515","Basile","Louisiana","LA","Evangeline","039","","","30.4978","-92.5736","4"],"70524":["US","70524","Chataignier","Louisiana","LA","Evangeline","039","","","30.5709","-92.3202","4"],"70554":["US","70554","Mamou","Louisiana","LA","Evangeline","039","","","30.6496","-92.4196","4"],"70576":["US","70576","Pine Prairie","Louisiana","LA","Evangeline","039","","","30.7831","-92.4163","4"],"70580":["US","70580","Reddell","Louisiana","LA","Evangeline","039","","","30.675","-92.4265","4"],"70585":["US","70585","Turkey Creek","Louisiana","LA","Evangeline","039","","","30.8707","-92.404","4"],"70586":["US","70586","Ville Platte","Louisiana","LA","Evangeline","039","","","30.6924","-92.2737","4"],"70513":["US","70513","Avery Island","Louisiana","LA","Iberia","045","","","29.8981","-91.9062","4"],"70544":["US","70544","Jeanerette","Louisiana","LA","Iberia","045","","","29.9032","-91.6544","4"],"70552":["US","70552","Loreauville","Louisiana","LA","Iberia","045","","","30.0683","-91.6596","4"],"70560":["US","70560","New Iberia","Louisiana","LA","Iberia","045","","","30.001","-91.82","4"],"70562":["US","70562","New Iberia","Louisiana","LA","Iberia","045","","","30.0035","-91.8187","4"],"70563":["US","70563","New Iberia","Louisiana","LA","Iberia","045","","","30.0245","-91.7496","4"],"70569":["US","70569","Lydia","Louisiana","LA","Iberia","045","","","29.9239","-91.7831","4"],"70721":["US","70721","Carville","Louisiana","LA","Iberville","047","","","30.2184","-91.0925","4"],"70740":["US","70740","Grosse Tete","Louisiana","LA","Iberville","047","","","30.3879","-91.4383","4"],"70757":["US","70757","Maringouin","Louisiana","LA","Iberville","047","","","30.4626","-91.5099","4"],"70764":["US","70764","Plaquemine","Louisiana","LA","Iberville","047","","","30.2684","-91.2524","4"],"70765":["US","70765","Plaquemine","Louisiana","LA","Iberville","047","","","30.2891","-91.2343","4"],"70772":["US","70772","Rosedale","Louisiana","LA","Iberville","047","","","30.4408","-91.4562","4"],"70776":["US","70776","Saint Gabriel","Louisiana","LA","Iberville","047","","","30.2528","-91.0857","4"],"70780":["US","70780","Sunshine","Louisiana","LA","Iberville","047","","","30.2982","-91.1799","4"],"70788":["US","70788","White Castle","Louisiana","LA","Iberville","047","","","30.1545","-91.1773","4"],"70001":["US","70001","Metairie","Louisiana","LA","Jefferson Parish","051","","","29.9871","-90.1695","4"],"70002":["US","70002","Metairie","Louisiana","LA","Jefferson Parish","051","","","30.0098","-90.163","4"],"70003":["US","70003","Metairie","Louisiana","LA","Jefferson Parish","051","","","29.9975","-90.2146","4"],"70004":["US","70004","Metairie","Louisiana","LA","Jefferson Parish","051","","","29.9841","-90.1529","4"],"70005":["US","70005","Metairie","Louisiana","LA","Jefferson Parish","051","","","30.0005","-90.1331","4"],"70006":["US","70006","Metairie","Louisiana","LA","Jefferson Parish","051","","","30.0129","-90.1915","4"],"70009":["US","70009","Metairie","Louisiana","LA","Jefferson Parish","051","","","29.9841","-90.1529","4"],"70010":["US","70010","Metairie","Louisiana","LA","Jefferson Parish","051","","","29.9841","-90.1529","4"],"70011":["US","70011","Metairie","Louisiana","LA","Jefferson Parish","051","","","29.9841","-90.1529","4"],"70033":["US","70033","Metairie","Louisiana","LA","Jefferson Parish","051","","","29.9841","-90.1529","4"],"70036":["US","70036","Barataria","Louisiana","LA","Jefferson Parish","051","","","29.6964","-90.1122","4"],"70053":["US","70053","Gretna","Louisiana","LA","Jefferson Parish","051","","","29.9108","-90.0531","4"],"70054":["US","70054","Gretna","Louisiana","LA","Jefferson Parish","051","","","29.9146","-90.054","4"],"70055":["US","70055","Metairie","Louisiana","LA","Jefferson Parish","051","","","29.9841","-90.1529","4"],"70056":["US","70056","Gretna","Louisiana","LA","Jefferson Parish","051","","","29.8872","-90.0331","4"],"70058":["US","70058","Harvey","Louisiana","LA","Jefferson Parish","051","","","29.8725","-90.0673","4"],"70059":["US","70059","Harvey","Louisiana","LA","Jefferson Parish","051","","","29.9035","-90.0773","4"],"70060":["US","70060","Metairie","Louisiana","LA","Jefferson Parish","051","","","29.9841","-90.1529","4"],"70062":["US","70062","Kenner","Louisiana","LA","Jefferson Parish","051","","","29.9912","-90.2479","4"],"70063":["US","70063","Kenner","Louisiana","LA","Jefferson Parish","051","","","29.9941","-90.2417","4"],"70064":["US","70064","Kenner","Louisiana","LA","Jefferson Parish","051","","","29.9941","-90.2417","4"],"70065":["US","70065","Kenner","Louisiana","LA","Jefferson Parish","051","","","30.0252","-90.2522","4"],"70067":["US","70067","Lafitte","Louisiana","LA","Jefferson Parish","051","","","29.7143","-90.1052","4"],"70072":["US","70072","Marrero","Louisiana","LA","Jefferson Parish","051","","","29.8598","-90.1105","4"],"70073":["US","70073","Marrero","Louisiana","LA","Jefferson Parish","051","","","29.8994","-90.1004","4"],"70094":["US","70094","Westwego","Louisiana","LA","Jefferson Parish","051","","","29.8973","-90.2033","4"],"70096":["US","70096","Westwego","Louisiana","LA","Jefferson Parish","051","","","29.906","-90.1423","4"],"70097":["US","70097","Kenner","Louisiana","LA","Jefferson Parish","051","","","29.9565","-90.2635","4"],"70121":["US","70121","New Orleans","Louisiana","LA","Jefferson Parish","051","","","29.9614","-90.1577","4"],"70123":["US","70123","New Orleans","Louisiana","LA","Jefferson Parish","051","","","29.9511","-90.206","4"],"70141":["US","70141","New Orleans","Louisiana","LA","Jefferson Parish","051","","","29.9546","-90.0751","4"],"70181":["US","70181","New Orleans","Louisiana","LA","Jefferson Parish","051","","","29.6779","-90.0901","4"],"70183":["US","70183","New Orleans","Louisiana","LA","Jefferson Parish","051","","","29.9546","-90.0751","4"],"70358":["US","70358","Grand Isle","Louisiana","LA","Jefferson Parish","051","","","29.2297","-90.0088","4"],"70532":["US","70532","Elton","Louisiana","LA","Jefferson Davis","053","","","30.4715","-92.6996","4"],"70546":["US","70546","Jennings","Louisiana","LA","Jefferson Davis","053","","","30.2201","-92.6574","4"],"70549":["US","70549","Lake Arthur","Louisiana","LA","Jefferson Davis","053","","","30.091","-92.6825","4"],"70581":["US","70581","Roanoke","Louisiana","LA","Jefferson Davis","053","","","30.2464","-92.7421","4"],"70591":["US","70591","Welsh","Louisiana","LA","Jefferson Davis","053","","","30.2363","-92.819","4"],"70640":["US","70640","Fenton","Louisiana","LA","Jefferson Davis","053","","","30.3655","-92.9122","4"],"70650":["US","70650","Lacassine","Louisiana","LA","Jefferson Davis","053","","","30.2374","-92.9232","4"],"70501":["US","70501","Lafayette","Louisiana","LA","Lafayette","055","","","30.2361","-92.0083","4"],"70502":["US","70502","Lafayette","Louisiana","LA","Lafayette","055","","","30.2241","-92.0198","4"],"70503":["US","70503","Lafayette","Louisiana","LA","Lafayette","055","","","30.1843","-92.0497","4"],"70504":["US","70504","Lafayette","Louisiana","LA","Lafayette","055","","","30.2139","-92.0187","4"],"70505":["US","70505","Lafayette","Louisiana","LA","Lafayette","055","","","30.2023","-92.0188","4"],"70506":["US","70506","Lafayette","Louisiana","LA","Lafayette","055","","","30.2077","-92.0656","4"],"70507":["US","70507","Lafayette","Louisiana","LA","Lafayette","055","","","30.2813","-92.016","4"],"70508":["US","70508","Lafayette","Louisiana","LA","Lafayette","055","","","30.1582","-92.0236","4"],"70509":["US","70509","Lafayette","Louisiana","LA","Lafayette","055","","","30.1565","-92","4"],"70518":["US","70518","Broussard","Louisiana","LA","Lafayette","055","","","30.1219","-91.9502","4"],"70520":["US","70520","Carencro","Louisiana","LA","Lafayette","055","","","30.3244","-92.0423","4"],"70529":["US","70529","Duson","Louisiana","LA","Lafayette","055","","","30.1912","-92.1525","4"],"70558":["US","70558","Milton","Louisiana","LA","Lafayette","055","","","30.1038","-92.0765","4"],"70583":["US","70583","Scott","Louisiana","LA","Lafayette","055","","","30.2504","-92.0981","4"],"70592":["US","70592","Youngsville","Louisiana","LA","Lafayette","055","","","30.0975","-92.0096","4"],"70593":["US","70593","Lafayette","Louisiana","LA","Lafayette","055","","","30.2081","-92.0951","4"],"70596":["US","70596","Lafayette","Louisiana","LA","Lafayette","055","","","30.2241","-92.0198","4"],"70598":["US","70598","Lafayette","Louisiana","LA","Lafayette","055","","","30.2081","-92.0951","4"],"70301":["US","70301","Thibodaux","Louisiana","LA","Lafourche","057","","","29.7992","-90.8096","4"],"70302":["US","70302","Thibodaux","Louisiana","LA","Lafourche","057","","","29.7958","-90.8229","4"],"70310":["US","70310","Thibodaux","Louisiana","LA","Lafourche","057","","","29.8033","-90.8169","4"],"70345":["US","70345","Cut Off","Louisiana","LA","Lafourche","057","","","29.5232","-90.3393","4"],"70354":["US","70354","Galliano","Louisiana","LA","Lafourche","057","","","29.4311","-90.2981","4"],"70355":["US","70355","Gheens","Louisiana","LA","Lafourche","057","","","29.7076","-90.4849","4"],"70357":["US","70357","Golden Meadow","Louisiana","LA","Lafourche","057","","","29.3821","-90.2639","4"],"70371":["US","70371","Kraemer","Louisiana","LA","Lafourche","057","","","29.8652","-90.5962","4"],"70373":["US","70373","Larose","Louisiana","LA","Lafourche","057","","","29.5724","-90.3817","4"],"70374":["US","70374","Lockport","Louisiana","LA","Lafourche","057","","","29.6155","-90.4442","4"],"70375":["US","70375","Mathews","Louisiana","LA","Lafourche","057","","","29.6938","-90.5496","4"],"70394":["US","70394","Raceland","Louisiana","LA","Lafourche","057","","","29.7178","-90.5999","4"],"70449":["US","70449","Maurepas","Louisiana","LA","Livingston","063","","","30.2716","-90.7043","4"],"70462":["US","70462","Springfield","Louisiana","LA","Livingston","063","","","30.4157","-90.5775","4"],"70706":["US","70706","Denham Springs","Louisiana","LA","Livingston","063","","","30.6085","-90.9038","4"],"70711":["US","70711","Albany","Louisiana","LA","Livingston","063","","","30.5149","-90.5964","4"],"70726":["US","70726","Denham Springs","Louisiana","LA","Livingston","063","","","30.459","-90.9027","4"],"70727":["US","70727","Denham Springs","Louisiana","LA","Livingston","063","","","30.3375","-90.8434","4"],"70733":["US","70733","French Settlement","Louisiana","LA","Livingston","063","","","30.2952","-90.7951","4"],"70744":["US","70744","Holden","Louisiana","LA","Livingston","063","","","30.5556","-90.6652","4"],"70754":["US","70754","Livingston","Louisiana","LA","Livingston","063","","","30.4741","-90.7673","4"],"70785":["US","70785","Walker","Louisiana","LA","Livingston","063","","","30.5247","-90.8557","4"],"70786":["US","70786","Watson","Louisiana","LA","Livingston","063","","","30.5502","-90.9582","4"],"70112":["US","70112","New Orleans","Louisiana","LA","Orleans","071","","","29.9605","-90.0753","4"],"70113":["US","70113","New Orleans","Louisiana","LA","Orleans","071","","","29.9405","-90.0848","4"],"70114":["US","70114","New Orleans","Louisiana","LA","Orleans","071","","","29.9379","-90.0331","4"],"70115":["US","70115","New Orleans","Louisiana","LA","Orleans","071","","","29.9289","-90.1005","4"],"70116":["US","70116","New Orleans","Louisiana","LA","Orleans","071","","","29.9686","-90.0646","4"],"70117":["US","70117","New Orleans","Louisiana","LA","Orleans","071","","","29.9703","-90.0312","4"],"70118":["US","70118","New Orleans","Louisiana","LA","Orleans","071","","","29.9504","-90.1236","4"],"70119":["US","70119","New Orleans","Louisiana","LA","Orleans","071","","","29.9746","-90.0852","4"],"70122":["US","70122","New Orleans","Louisiana","LA","Orleans","071","","","30.0056","-90.0644","4"],"70124":["US","70124","New Orleans","Louisiana","LA","Orleans","071","","","30.0071","-90.1094","4"],"70125":["US","70125","New Orleans","Louisiana","LA","Orleans","071","","","29.9512","-90.1028","4"],"70126":["US","70126","New Orleans","Louisiana","LA","Orleans","071","","","29.9987","-90.0446","4"],"70127":["US","70127","New Orleans","Louisiana","LA","Orleans","071","","","30.0313","-89.9758","4"],"70128":["US","70128","New Orleans","Louisiana","LA","Orleans","071","","","30.0487","-89.9585","4"],"70129":["US","70129","New Orleans","Louisiana","LA","Orleans","071","","","30.0877","-89.8462","4"],"70130":["US","70130","New Orleans","Louisiana","LA","Orleans","071","","","29.9324","-90.0739","4"],"70131":["US","70131","New Orleans","Louisiana","LA","Orleans","071","","","29.9168","-89.996","4"],"70139":["US","70139","New Orleans","Louisiana","LA","Orleans","071","","","29.9546","-90.0751","4"],"70142":["US","70142","New Orleans","Louisiana","LA","Orleans","071","","","29.9546","-90.0751","4"],"70143":["US","70143","New Orleans","Louisiana","LA","Orleans","071","","","29.9546","-90.0751","4"],"70145":["US","70145","New Orleans","Louisiana","LA","Orleans","071","","","29.9546","-90.0751","4"],"70146":["US","70146","New Orleans","Louisiana","LA","Orleans","071","","","29.9546","-90.0751","4"],"70148":["US","70148","New Orleans","Louisiana","LA","Orleans","071","","","30.0309","-90.068","4"],"70150":["US","70150","New Orleans","Louisiana","LA","Orleans","071","","","29.9546","-90.0751","4"],"70151":["US","70151","New Orleans","Louisiana","LA","Orleans","071","","","29.9546","-90.0751","4"],"70152":["US","70152","New Orleans","Louisiana","LA","Orleans","071","","","29.9546","-90.0751","4"],"70153":["US","70153","New Orleans","Louisiana","LA","Orleans","071","","","29.9546","-90.0751","4"],"70154":["US","70154","New Orleans","Louisiana","LA","Orleans","071","","","29.9546","-90.0751","4"],"70156":["US","70156","New Orleans","Louisiana","LA","Orleans","071","","","29.9546","-90.0751","4"],"70157":["US","70157","New Orleans","Louisiana","LA","Orleans","071","","","29.9546","-90.0751","4"],"70158":["US","70158","New Orleans","Louisiana","LA","Orleans","071","","","29.9229","-90.0709","4"],"70159":["US","70159","New Orleans","Louisiana","LA","Orleans","071","","","29.9546","-90.0751","4"],"70160":["US","70160","New Orleans","Louisiana","LA","Orleans","071","","","29.9546","-90.0751","4"],"70161":["US","70161","New Orleans","Louisiana","LA","Orleans","071","","","29.9546","-90.0751","4"],"70162":["US","70162","New Orleans","Louisiana","LA","Orleans","071","","","29.9546","-90.0751","4"],"70163":["US","70163","New Orleans","Louisiana","LA","Orleans","071","","","29.95","-90.0755","4"],"70164":["US","70164","New Orleans","Louisiana","LA","Orleans","071","","","29.9546","-90.0751","4"],"70165":["US","70165","New Orleans","Louisiana","LA","Orleans","071","","","29.9546","-90.0751","4"],"70166":["US","70166","New Orleans","Louisiana","LA","Orleans","071","","","29.9546","-90.0751","4"],"70167":["US","70167","New Orleans","Louisiana","LA","Orleans","071","","","29.9546","-90.0751","4"],"70170":["US","70170","New Orleans","Louisiana","LA","Orleans","071","","","29.9546","-90.0751","4"],"70172":["US","70172","New Orleans","Louisiana","LA","Orleans","071","","","29.9546","-90.0751","4"],"70174":["US","70174","New Orleans","Louisiana","LA","Orleans","071","","","29.9546","-90.0751","4"],"70175":["US","70175","New Orleans","Louisiana","LA","Orleans","071","","","29.9546","-90.0751","4"],"70176":["US","70176","New Orleans","Louisiana","LA","Orleans","071","","","29.9546","-90.0751","4"],"70177":["US","70177","New Orleans","Louisiana","LA","Orleans","071","","","29.9546","-90.0751","4"],"70178":["US","70178","New Orleans","Louisiana","LA","Orleans","071","","","29.9546","-90.0751","4"],"70179":["US","70179","New Orleans","Louisiana","LA","Orleans","071","","","29.9546","-90.0751","4"],"70182":["US","70182","New Orleans","Louisiana","LA","Orleans","071","","","29.9546","-90.0751","4"],"70184":["US","70184","New Orleans","Louisiana","LA","Orleans","071","","","29.9546","-90.0751","4"],"70185":["US","70185","New Orleans","Louisiana","LA","Orleans","071","","","29.9546","-90.0751","4"],"70186":["US","70186","New Orleans","Louisiana","LA","Orleans","071","","","29.9546","-90.0751","4"],"70187":["US","70187","New Orleans","Louisiana","LA","Orleans","071","","","29.9546","-90.0751","4"],"70189":["US","70189","New Orleans","Louisiana","LA","Orleans","071","","","29.9546","-90.0751","4"],"70190":["US","70190","New Orleans","Louisiana","LA","Orleans","071","","","29.9546","-90.0751","4"],"70195":["US","70195","New Orleans","Louisiana","LA","Orleans","071","","","29.9546","-90.0751","4"],"70037":["US","70037","Belle Chasse","Louisiana","LA","Plaquemines Parish","075","","","29.8345","-90.0042","4"],"70038":["US","70038","Boothville","Louisiana","LA","Plaquemines Parish","075","","","29.3079","-89.3814","4"],"70040":["US","70040","Braithwaite","Louisiana","LA","Plaquemines Parish","075","","","29.7361","-89.9197","4"],"70041":["US","70041","Buras","Louisiana","LA","Plaquemines Parish","075","","","29.3519","-89.5242","4"],"70050":["US","70050","Empire","Louisiana","LA","Plaquemines Parish","075","","","29.3814","-89.5926","4"],"70081":["US","70081","Pilottown","Louisiana","LA","Plaquemines Parish","075","","","29.1816","-89.2576","4"],"70082":["US","70082","Pointe A La Hache","Louisiana","LA","Plaquemines Parish","075","","","29.542","-89.7512","4"],"70083":["US","70083","Port Sulphur","Louisiana","LA","Plaquemines Parish","075","","","29.47","-89.6847","4"],"70091":["US","70091","Venice","Louisiana","LA","Plaquemines Parish","075","","","29.2659","-89.3761","4"],"70093":["US","70093","Belle Chasse","Louisiana","LA","Plaquemines Parish","075","","","29.8549","-89.9906","4"],"70715":["US","70715","Batchelor","Louisiana","LA","Pointe Coupee","077","","","30.8298","-91.6944","4"],"70732":["US","70732","Fordoche","Louisiana","LA","Pointe Coupee","077","","","30.596","-91.6165","4"],"70736":["US","70736","Glynn","Louisiana","LA","Pointe Coupee","077","","","30.6376","-91.3423","4"],"70747":["US","70747","Innis","Louisiana","LA","Pointe Coupee","077","","","30.8736","-91.6766","4"],"70749":["US","70749","Jarreau","Louisiana","LA","Pointe Coupee","077","","","30.6326","-91.4332","4"],"70752":["US","70752","Lakeland","Louisiana","LA","Pointe Coupee","077","","","30.5799","-91.4217","4"],"70753":["US","70753","Lettsworth","Louisiana","LA","Pointe Coupee","077","","","30.9324","-91.7403","4"],"70755":["US","70755","Livonia","Louisiana","LA","Pointe Coupee","077","","","30.5524","-91.5332","4"],"70756":["US","70756","Lottie","Louisiana","LA","Pointe Coupee","077","","","30.5563","-91.6418","4"],"70759":["US","70759","Morganza","Louisiana","LA","Pointe Coupee","077","","","30.7245","-91.5959","4"],"70760":["US","70760","New Roads","Louisiana","LA","Pointe Coupee","077","","","30.7014","-91.4421","4"],"70762":["US","70762","Oscar","Louisiana","LA","Pointe Coupee","077","","","30.5983","-91.4577","4"],"70773":["US","70773","Rougon","Louisiana","LA","Pointe Coupee","077","","","30.6035","-91.3813","4"],"70783":["US","70783","Ventress","Louisiana","LA","Pointe Coupee","077","","","30.6814","-91.4033","4"],"70032":["US","70032","Arabi","Louisiana","LA","St. Bernard","087","","","29.9612","-89.9965","4"],"70043":["US","70043","Chalmette","Louisiana","LA","St. Bernard","087","","","29.9466","-89.9611","4"],"70044":["US","70044","Chalmette","Louisiana","LA","St. Bernard","087","","","29.9676","-89.9514","4"],"70075":["US","70075","Meraux","Louisiana","LA","St. Bernard","087","","","29.9335","-89.9214","4"],"70085":["US","70085","Saint Bernard","Louisiana","LA","St. Bernard","087","","","29.8611","-89.8364","4"],"70092":["US","70092","Violet","Louisiana","LA","St. Bernard","087","","","29.9043","-89.896","4"],"70030":["US","70030","Des Allemands","Louisiana","LA","St. Charles","089","","","29.8134","-90.4407","4"],"70031":["US","70031","Ama","Louisiana","LA","St. Charles","089","","","29.9435","-90.2925","4"],"70039":["US","70039","Boutte","Louisiana","LA","St. Charles","089","","","29.8973","-90.3934","4"],"70047":["US","70047","Destrehan","Louisiana","LA","St. Charles","089","","","29.9642","-90.3682","4"],"70057":["US","70057","Hahnville","Louisiana","LA","St. Charles","089","","","29.9668","-90.4082","4"],"70070":["US","70070","Luling","Louisiana","LA","St. Charles","089","","","29.9251","-90.3693","4"],"70078":["US","70078","New Sarpy","Louisiana","LA","St. Charles","089","","","29.9817","-90.3859","4"],"70079":["US","70079","Norco","Louisiana","LA","St. Charles","089","","","30.0057","-90.4198","4"],"70080":["US","70080","Paradis","Louisiana","LA","St. Charles","089","","","29.877","-90.4352","4"],"70087":["US","70087","Saint Rose","Louisiana","LA","St. Charles","089","","","29.9581","-90.3124","4"],"70441":["US","70441","Greensburg","Louisiana","LA","St. Helena","091","","","30.8647","-90.7256","4"],"70453":["US","70453","Pine Grove","Louisiana","LA","St. Helena","091","","","30.7032","-90.7672","4"],"70052":["US","70052","Gramercy","Louisiana","LA","St. James","093","","","30.0527","-90.6902","4"],"70071":["US","70071","Lutcher","Louisiana","LA","St. James","093","","","30.0447","-90.7008","4"],"70086":["US","70086","Saint James","Louisiana","LA","St. James","093","","","30.0276","-90.8605","4"],"70090":["US","70090","Vacherie","Louisiana","LA","St. James","093","","","29.9694","-90.7097","4"],"70723":["US","70723","Convent","Louisiana","LA","St. James","093","","","30.0208","-90.8298","4"],"70743":["US","70743","Hester","Louisiana","LA","St. James","093","","","30.0206","-90.7814","4"],"70763":["US","70763","Paulina","Louisiana","LA","St. James","093","","","30.0352","-90.7374","4"],"70792":["US","70792","Uncle Sam","Louisiana","LA","St. James","093","","","30.0279","-90.8028","4"],"70049":["US","70049","Edgard","Louisiana","LA","St. John the Baptist","095","","","30.0319","-90.5817","4"],"70051":["US","70051","Garyville","Louisiana","LA","St. John the Baptist","095","","","30.0535","-90.6201","4"],"70068":["US","70068","La Place","Louisiana","LA","St. John the Baptist","095","","","30.0777","-90.4895","1"],"70069":["US","70069","La Place","Louisiana","LA","St. John the Baptist","095","","","30.0912","-90.4832","1"],"70076":["US","70076","Mount Airy","Louisiana","LA","St. John the Baptist","095","","","30.0575","-90.6369","4"],"70084":["US","70084","Reserve","Louisiana","LA","St. John the Baptist","095","","","30.0603","-90.5518","4"],"70512":["US","70512","Arnaudville","Louisiana","LA","St. Landry","097","","","30.3981","-91.9263","4"],"70535":["US","70535","Eunice","Louisiana","LA","St. Landry","097","","","30.5116","-92.3985","4"],"70541":["US","70541","Grand Coteau","Louisiana","LA","St. Landry","097","","","30.4201","-92.0462","4"],"70550":["US","70550","Lawtell","Louisiana","LA","St. Landry","097","","","30.5165","-92.1841","4"],"70551":["US","70551","Leonville","Louisiana","LA","St. Landry","097","","","30.4752","-91.9737","4"],"70570":["US","70570","Opelousas","Louisiana","LA","St. Landry","097","","","30.5144","-92.0897","4"],"70571":["US","70571","Opelousas","Louisiana","LA","St. Landry","097","","","30.5335","-92.0815","4"],"70577":["US","70577","Port Barre","Louisiana","LA","St. Landry","097","","","30.5478","-91.9286","4"],"70584":["US","70584","Sunset","Louisiana","LA","St. Landry","097","","","30.3884","-92.0934","4"],"70589":["US","70589","Washington","Louisiana","LA","St. Landry","097","","","30.6839","-92.0252","4"],"70750":["US","70750","Krotz Springs","Louisiana","LA","St. Landry","097","","","30.5379","-91.7563","4"],"70517":["US","70517","Breaux Bridge","Louisiana","LA","St. Martin","099","","","30.2948","-91.8296","4"],"70519":["US","70519","Cade","Louisiana","LA","St. Martin","099","","","30.0797","-91.9114","4"],"70521":["US","70521","Cecilia","Louisiana","LA","St. Martin","099","","","30.3364","-91.8492","4"],"70582":["US","70582","Saint Martinville","Louisiana","LA","St. Martin","099","","","30.2237","-91.7794","4"],"70340":["US","70340","Amelia","Louisiana","LA","St. Mary","101","","","29.6663","-91.102","4"],"70342":["US","70342","Berwick","Louisiana","LA","St. Mary","101","","","29.6929","-91.2518","4"],"70380":["US","70380","Morgan City","Louisiana","LA","St. Mary","101","","","29.6977","-91.2654","4"],"70381":["US","70381","Morgan City","Louisiana","LA","St. Mary","101","","","29.6946","-91.2593","4"],"70392":["US","70392","Patterson","Louisiana","LA","St. Mary","101","","","29.6967","-91.2812","4"],"70514":["US","70514","Baldwin","Louisiana","LA","St. Mary","101","","","29.8488","-91.5458","4"],"70522":["US","70522","Centerville","Louisiana","LA","St. Mary","101","","","29.7523","-91.4397","4"],"70523":["US","70523","Charenton","Louisiana","LA","St. Mary","101","","","29.8796","-91.5337","4"],"70538":["US","70538","Franklin","Louisiana","LA","St. Mary","101","","","29.7857","-91.5026","4"],"70540":["US","70540","Garden City","Louisiana","LA","St. Mary","101","","","29.7633","-91.467","4"],"70420":["US","70420","Abita Springs","Louisiana","LA","St. Tammany","103","","","30.4837","-90.0041","4"],"70431":["US","70431","Bush","Louisiana","LA","St. Tammany","103","","","30.6134","-89.9557","4"],"70433":["US","70433","Covington","Louisiana","LA","St. Tammany","103","","","30.4876","-90.0959","4"],"70434":["US","70434","Covington","Louisiana","LA","St. Tammany","103","","","30.4755","-90.1004","4"],"70435":["US","70435","Covington","Louisiana","LA","St. Tammany","103","","","30.5661","-90.1098","4"],"70437":["US","70437","Folsom","Louisiana","LA","St. Tammany","103","","","30.6145","-90.1879","4"],"70445":["US","70445","Lacombe","Louisiana","LA","St. Tammany","103","","","30.322","-89.9297","4"],"70447":["US","70447","Madisonville","Louisiana","LA","St. Tammany","103","","","30.4287","-90.1773","4"],"70448":["US","70448","Mandeville","Louisiana","LA","St. Tammany","103","","","30.3666","-90.0487","4"],"70452":["US","70452","Pearl River","Louisiana","LA","St. Tammany","103","","","30.3944","-89.7732","4"],"70457":["US","70457","Saint Benedict","Louisiana","LA","St. Tammany","103","","","30.5269","-90.1126","4"],"70458":["US","70458","Slidell","Louisiana","LA","St. Tammany","103","","","30.2784","-89.7712","4"],"70459":["US","70459","Slidell","Louisiana","LA","St. Tammany","103","","","30.4255","-89.8813","4"],"70460":["US","70460","Slidell","Louisiana","LA","St. Tammany","103","","","30.2916","-89.8129","4"],"70461":["US","70461","Slidell","Louisiana","LA","St. Tammany","103","","","30.2726","-89.729","4"],"70463":["US","70463","Sun","Louisiana","LA","St. Tammany","103","","","30.6491","-89.8926","4"],"70464":["US","70464","Talisheek","Louisiana","LA","St. Tammany","103","","","30.5347","-89.8859","4"],"70469":["US","70469","Slidell","Louisiana","LA","St. Tammany","103","","","30.2752","-89.7812","4"],"70470":["US","70470","Mandeville","Louisiana","LA","St. Tammany","103","","","30.4255","-89.8813","4"],"70471":["US","70471","Mandeville","Louisiana","LA","St. Tammany","103","","","30.4207","-90.0589","4"],"70401":["US","70401","Hammond","Louisiana","LA","Tangipahoa","105","","","30.5191","-90.4879","4"],"70402":["US","70402","Hammond","Louisiana","LA","Tangipahoa","105","","","30.514","-90.4804","4"],"70403":["US","70403","Hammond","Louisiana","LA","Tangipahoa","105","","","30.4911","-90.4697","4"],"70404":["US","70404","Hammond","Louisiana","LA","Tangipahoa","105","","","30.5046","-90.4629","4"],"70421":["US","70421","Akers","Louisiana","LA","Tangipahoa","105","","","30.2902","-90.4018","4"],"70422":["US","70422","Amite","Louisiana","LA","Tangipahoa","105","","","30.7266","-90.509","4"],"70436":["US","70436","Fluker","Louisiana","LA","Tangipahoa","105","","","30.8128","-90.5207","4"],"70442":["US","70442","Husser","Louisiana","LA","Tangipahoa","105","","","30.692","-90.339","4"],"70443":["US","70443","Independence","Louisiana","LA","Tangipahoa","105","","","30.6351","-90.5277","4"],"70444":["US","70444","Kentwood","Louisiana","LA","Tangipahoa","105","","","30.8892","-90.4728","4"],"70446":["US","70446","Loranger","Louisiana","LA","Tangipahoa","105","","","30.5884","-90.3567","4"],"70451":["US","70451","Natalbany","Louisiana","LA","Tangipahoa","105","","","30.5519","-90.4859","4"],"70454":["US","70454","Ponchatoula","Louisiana","LA","Tangipahoa","105","","","30.4406","-90.4422","4"],"70455":["US","70455","Robert","Louisiana","LA","Tangipahoa","105","","","30.5063","-90.3352","4"],"70456":["US","70456","Roseland","Louisiana","LA","Tangipahoa","105","","","30.7717","-90.5243","4"],"70465":["US","70465","Tangipahoa","Louisiana","LA","Tangipahoa","105","","","30.8764","-90.5089","4"],"70466":["US","70466","Tickfaw","Louisiana","LA","Tangipahoa","105","","","30.5668","-90.482","4"],"70343":["US","70343","Bourg","Louisiana","LA","Terrebonne","109","","","29.5485","-90.6087","4"],"70344":["US","70344","Chauvin","Louisiana","LA","Terrebonne","109","","","29.4634","-90.598","4"],"70352":["US","70352","Donner","Louisiana","LA","Terrebonne","109","","","29.6964","-90.9444","4"],"70353":["US","70353","Dulac","Louisiana","LA","Terrebonne","109","","","29.3695","-90.697","4"],"70356":["US","70356","Gibson","Louisiana","LA","Terrebonne","109","","","29.6625","-90.9776","4"],"70359":["US","70359","Gray","Louisiana","LA","Terrebonne","109","","","29.6903","-90.7807","4"],"70360":["US","70360","Houma","Louisiana","LA","Terrebonne","109","","","29.5943","-90.7548","4"],"70361":["US","70361","Houma","Louisiana","LA","Terrebonne","109","","","29.5958","-90.7195","4"],"70363":["US","70363","Houma","Louisiana","LA","Terrebonne","109","","","29.5601","-90.6917","4"],"70364":["US","70364","Houma","Louisiana","LA","Terrebonne","109","","","29.6299","-90.7268","4"],"70377":["US","70377","Montegut","Louisiana","LA","Terrebonne","109","","","29.4744","-90.544","4"],"70395":["US","70395","Schriever","Louisiana","LA","Terrebonne","109","","","29.7123","-90.8513","4"],"70397":["US","70397","Theriot","Louisiana","LA","Terrebonne","109","","","29.4516","-90.7651","4"],"70510":["US","70510","Abbeville","Louisiana","LA","Vermilion","113","","","29.9466","-92.2416","4"],"70511":["US","70511","Abbeville","Louisiana","LA","Vermilion","113","","","29.9747","-92.1343","4"],"70528":["US","70528","Delcambre","Louisiana","LA","Vermilion","113","","","29.9474","-91.9889","4"],"70533":["US","70533","Erath","Louisiana","LA","Vermilion","113","","","29.9522","-92.0343","4"],"70542":["US","70542","Gueydan","Louisiana","LA","Vermilion","113","","","30.0255","-92.5338","4"],"70548":["US","70548","Kaplan","Louisiana","LA","Vermilion","113","","","29.9771","-92.3025","4"],"70555":["US","70555","Maurice","Louisiana","LA","Vermilion","113","","","30.0722","-92.107","4"],"70575":["US","70575","Perry","Louisiana","LA","Vermilion","113","","","29.9485","-92.1571","4"],"70639":["US","70639","Evans","Louisiana","LA","Vernon","115","","","30.9684","-93.5203","4"],"70656":["US","70656","Pitkin","Louisiana","LA","Vernon","115","","","30.933","-92.9548","4"],"70659":["US","70659","Rosepine","Louisiana","LA","Vernon","115","","","30.9243","-93.2749","4"],"70426":["US","70426","Angie","Louisiana","LA","Washington","117","","","30.9224","-89.8567","4"],"70427":["US","70427","Bogalusa","Louisiana","LA","Washington","117","","","30.7733","-89.8653","4"],"70429":["US","70429","Bogalusa","Louisiana","LA","Washington","117","","","30.791","-89.8487","4"],"70438":["US","70438","Franklinton","Louisiana","LA","Washington","117","","","30.8577","-90.1155","4"],"70450":["US","70450","Mount Hermon","Louisiana","LA","Washington","117","","","30.9536","-90.2769","4"],"70467":["US","70467","Varnado","Louisiana","LA","Washington","117","","","30.8938","-89.8295","4"],"70710":["US","70710","Addis","Louisiana","LA","West Baton Rouge","121","","","30.3557","-91.2613","4"],"70719":["US","70719","Brusly","Louisiana","LA","West Baton Rouge","121","","","30.3877","-91.2526","4"],"70729":["US","70729","Erwinville","Louisiana","LA","West Baton Rouge","121","","","30.548","-91.4187","4"],"70767":["US","70767","Port Allen","Louisiana","LA","West Baton Rouge","121","","","30.472","-91.2541","4"],"70712":["US","70712","Angola","Louisiana","LA","West Feliciana","125","","","30.9656","-91.5979","4"],"70775":["US","70775","Saint Francisville","Louisiana","LA","West Feliciana","125","","","30.8694","-91.4186","4"],"70782":["US","70782","Tunica","Louisiana","LA","West Feliciana","125","","","30.9601","-91.5396","4"],"70784":["US","70784","Wakefield","Louisiana","LA","West Feliciana","125","","","30.9175","-91.3581","4"],"70787":["US","70787","Weyanoke","Louisiana","LA","West Feliciana","125","","","30.9468","-91.4612","4"]}