{"72003":["US","72003","Almyra","Arkansas","AR","Arkansas","001","","","34.4146","-91.431","4"],"72026":["US","72026","Casscoe","Arkansas","AR","Arkansas","001","","","34.5095","-91.299","4"],"72038":["US","72038","Crocketts Bluff","Arkansas","AR","Arkansas","001","","","34.4528","-91.2692","4"],"72042":["US","72042","De Witt","Arkansas","AR","Arkansas","001","","","34.2853","-91.3336","4"],"72048":["US","72048","Ethel","Arkansas","AR","Arkansas","001","","","34.2435","-91.1398","4"],"72055":["US","72055","Gillett","Arkansas","AR","Arkansas","001","","","34.1218","-91.38","4"],"72073":["US","72073","Humphrey","Arkansas","AR","Arkansas","001","","","34.4034","-91.679","4"],"72140":["US","72140","Saint Charles","Arkansas","AR","Arkansas","001","","","34.3878","-91.1463","4"],"72160":["US","72160","Stuttgart","Arkansas","AR","Arkansas","001","","","34.4854","-91.5487","4"],"72166":["US","72166","Tichnor","Arkansas","AR","Arkansas","001","","","34.0893","-91.2437","4"],"72537":["US","72537","Gamaliel","Arkansas","AR","Baxter","005","","","36.4618","-92.2284","4"],"72544":["US","72544","Henderson","Arkansas","AR","Baxter","005","","","36.4105","-92.1951","4"],"72617":["US","72617","Big Flat","Arkansas","AR","Baxter","005","","","36.0068","-92.3917","4"],"72623":["US","72623","Clarkridge","Arkansas","AR","Baxter","005","","","36.4724","-92.3296","4"],"72626":["US","72626","Cotter","Arkansas","AR","Baxter","005","","","36.2712","-92.5354","4"],"72635":["US","72635","Gassville","Arkansas","AR","Baxter","005","","","36.3175","-92.4736","4"],"72642":["US","72642","Lakeview","Arkansas","AR","Baxter","005","","","36.373","-92.5422","4"],"72651":["US","72651","Midway","Arkansas","AR","Baxter","005","","","36.3933","-92.4881","4"],"72653":["US","72653","Mountain Home","Arkansas","AR","Baxter","005","","","36.3312","-92.3753","4"],"72654":["US","72654","Mountain Home","Arkansas","AR","Baxter","005","","","36.3353","-92.3852","4"],"72658":["US","72658","Norfork","Arkansas","AR","Baxter","005","","","36.2066","-92.273","4"],"72659":["US","72659","Norfork","Arkansas","AR","Baxter","005","","","36.2095","-92.2843","4"],"72711":["US","72711","Avoca","Arkansas","AR","Benton","007","","","36.4047","-94.0713","4"],"72712":["US","72712","Bentonville","Arkansas","AR","Benton","007","","","36.3577","-94.2224","4"],"72714":["US","72714","Bella Vista","Arkansas","AR","Benton","007","","","36.4676","-94.2166","4"],"72715":["US","72715","Bella Vista","Arkansas","AR","Benton","007","","","36.4677","-94.3209","4"],"72716":["US","72716","Bentonville","Arkansas","AR","Benton","007","","","36.3729","-94.2088","4"],"72718":["US","72718","Cave Springs","Arkansas","AR","Benton","007","","","36.2738","-94.2183","4"],"72719":["US","72719","Centerton","Arkansas","AR","Benton","007","","","36.367","-94.3089","4"],"72722":["US","72722","Decatur","Arkansas","AR","Benton","007","","","36.3347","-94.4534","4"],"72732":["US","72732","Garfield","Arkansas","AR","Benton","007","","","36.4288","-93.9512","4"],"72733":["US","72733","Gateway","Arkansas","AR","Benton","007","","","36.4864","-93.9277","4"],"72734":["US","72734","Gentry","Arkansas","AR","Benton","007","","","36.2652","-94.4751","4"],"72736":["US","72736","Gravette","Arkansas","AR","Benton","007","","","36.4155","-94.4779","4"],"72739":["US","72739","Hiwasse","Arkansas","AR","Benton","007","","","36.4416","-94.339","4"],"72745":["US","72745","Lowell","Arkansas","AR","Benton","007","","","36.2554","-94.1308","4"],"72747":["US","72747","Maysville","Arkansas","AR","Benton","007","","","36.3811","-94.5783","4"],"72751":["US","72751","Pea Ridge","Arkansas","AR","Benton","007","","","36.4539","-94.118","4"],"72756":["US","72756","Rogers","Arkansas","AR","Benton","007","","","36.3363","-94.1148","4"],"72757":["US","72757","Rogers","Arkansas","AR","Benton","007","","","36.332","-94.1185","4"],"72758":["US","72758","Rogers","Arkansas","AR","Benton","007","","","36.3169","-94.1545","4"],"72761":["US","72761","Siloam Springs","Arkansas","AR","Benton","007","","","36.18","-94.528","4"],"72768":["US","72768","Sulphur Springs","Arkansas","AR","Benton","007","","","36.4794","-94.4521","4"],"72260":["US","72260","Little Rock","Arkansas","AR","Boone","009","","","34.7399","-92.34","4"],"72601":["US","72601","Harrison","Arkansas","AR","Boone","009","","","36.2417","-93.1062","4"],"72602":["US","72602","Harrison","Arkansas","AR","Boone","009","","","36.2298","-93.1077","4"],"72611":["US","72611","Alpena","Arkansas","AR","Boone","009","","","36.2998","-93.2792","4"],"72615":["US","72615","Bergman","Arkansas","AR","Boone","009","","","36.3083","-93.0321","4"],"72630":["US","72630","Diamond City","Arkansas","AR","Boone","009","","","36.4645","-92.9202","4"],"72633":["US","72633","Everton","Arkansas","AR","Boone","009","","","36.1534","-92.915","4"],"72644":["US","72644","Lead Hill","Arkansas","AR","Boone","009","","","36.3848","-93.0039","4"],"72662":["US","72662","Omaha","Arkansas","AR","Boone","009","","","36.4612","-93.1888","4"],"72682":["US","72682","Valley Springs","Arkansas","AR","Boone","009","","","36.1351","-92.7541","4"],"72613":["US","72613","Beaver","Arkansas","AR","Carroll","015","","","36.4311","-93.6994","4"],"72616":["US","72616","Berryville","Arkansas","AR","Carroll","015","","","36.3519","-93.5587","4"],"72631":["US","72631","Eureka Springs","Arkansas","AR","Carroll","015","","","36.435","-93.7673","4"],"72632":["US","72632","Eureka Springs","Arkansas","AR","Carroll","015","","","36.4175","-93.7379","4"],"72638":["US","72638","Green Forest","Arkansas","AR","Carroll","015","","","36.3224","-93.4059","4"],"72660":["US","72660","Oak Grove","Arkansas","AR","Carroll","015","","","36.4613","-93.4321","4"],"72422":["US","72422","Corning","Arkansas","AR","Clay","021","","","36.4155","-90.587","4"],"72424":["US","72424","Datto","Arkansas","AR","Clay","021","","","36.3897","-90.7231","4"],"72430":["US","72430","Greenway","Arkansas","AR","Clay","021","","","36.3348","-90.2253","4"],"72435":["US","72435","Knobel","Arkansas","AR","Clay","021","","","36.3176","-90.599","4"],"72441":["US","72441","Mc Dougal","Arkansas","AR","Clay","021","","","36.437","-90.3837","1"],"72453":["US","72453","Peach Orchard","Arkansas","AR","Clay","021","","","36.283","-90.6702","4"],"72454":["US","72454","Piggott","Arkansas","AR","Clay","021","","","36.387","-90.1926","4"],"72456":["US","72456","Pollard","Arkansas","AR","Clay","021","","","36.4317","-90.2751","4"],"72461":["US","72461","Rector","Arkansas","AR","Clay","021","","","36.2672","-90.2702","4"],"72464":["US","72464","Saint Francis","Arkansas","AR","Clay","021","","","36.4534","-90.1454","4"],"72470":["US","72470","Success","Arkansas","AR","Clay","021","","","36.4536","-90.7281","4"],"72044":["US","72044","Edgemont","Arkansas","AR","Cleburne","023","","","35.6321","-92.157","4"],"72067":["US","72067","Higden","Arkansas","AR","Cleburne","023","","","35.5685","-92.1341","4"],"72130":["US","72130","Prim","Arkansas","AR","Cleburne","023","","","35.6674","-92.0933","4"],"72131":["US","72131","Quitman","Arkansas","AR","Cleburne","023","","","35.405","-92.1333","4"],"72179":["US","72179","Wilburn","Arkansas","AR","Cleburne","023","","","35.5106","-91.8648","4"],"72523":["US","72523","Concord","Arkansas","AR","Cleburne","023","","","35.6414","-91.8333","4"],"72530":["US","72530","Drasco","Arkansas","AR","Cleburne","023","","","35.6616","-91.9398","4"],"72543":["US","72543","Heber Springs","Arkansas","AR","Cleburne","023","","","35.5103","-92.0392","4"],"72545":["US","72545","Heber Springs","Arkansas","AR","Cleburne","023","","","35.5352","-92.0213","4"],"72546":["US","72546","Ida","Arkansas","AR","Cleburne","023","","","35.5816","-91.9305","4"],"72581":["US","72581","Tumbling Shoals","Arkansas","AR","Cleburne","023","","","35.547","-91.9704","4"],"72027":["US","72027","Center Ridge","Arkansas","AR","Conway","029","","","35.3981","-92.5582","4"],"72030":["US","72030","Cleveland","Arkansas","AR","Conway","029","","","35.3955","-92.702","4"],"72063":["US","72063","Hattieville","Arkansas","AR","Conway","029","","","35.2907","-92.7783","4"],"72080":["US","72080","Jerusalem","Arkansas","AR","Conway","029","","","35.5699","-92.8251","4"],"72107":["US","72107","Menifee","Arkansas","AR","Conway","029","","","35.1356","-92.5498","4"],"72110":["US","72110","Morrilton","Arkansas","AR","Conway","029","","","35.1692","-92.7354","4"],"72127":["US","72127","Plumerville","Arkansas","AR","Conway","029","","","35.1575","-92.6204","4"],"72156":["US","72156","Solgohachia","Arkansas","AR","Conway","029","","","35.2701","-92.6754","4"],"72157":["US","72157","Springfield","Arkansas","AR","Conway","029","","","35.2749","-92.5457","4"],"72401":["US","72401","Jonesboro","Arkansas","AR","Craighead","031","","","35.833","-90.6965","4"],"72402":["US","72402","Jonesboro","Arkansas","AR","Craighead","031","","","35.8088","-90.6529","4"],"72403":["US","72403","Jonesboro","Arkansas","AR","Craighead","031","","","35.8305","-90.7039","4"],"72404":["US","72404","Jonesboro","Arkansas","AR","Craighead","031","","","35.7792","-90.766","4"],"72411":["US","72411","Bay","Arkansas","AR","Craighead","031","","","35.7456","-90.5507","4"],"72414":["US","72414","Black Oak","Arkansas","AR","Craighead","031","","","35.8368","-90.4005","4"],"72416":["US","72416","Bono","Arkansas","AR","Craighead","031","","","35.9086","-90.7848","4"],"72417":["US","72417","Brookland","Arkansas","AR","Craighead","031","","","35.9165","-90.5762","4"],"72419":["US","72419","Caraway","Arkansas","AR","Craighead","031","","","35.759","-90.3358","4"],"72421":["US","72421","Cash","Arkansas","AR","Craighead","031","","","35.8301","-90.941","4"],"72427":["US","72427","Egypt","Arkansas","AR","Craighead","031","","","35.864","-90.9428","4"],"72437":["US","72437","Lake City","Arkansas","AR","Craighead","031","","","35.8171","-90.4423","4"],"72447":["US","72447","Monette","Arkansas","AR","Craighead","031","","","35.9002","-90.3437","4"],"72467":["US","72467","State University","Arkansas","AR","Craighead","031","","","35.8422","-90.6735","4"],"72921":["US","72921","Alma","Arkansas","AR","Crawford","033","","","35.5","-94.2073","4"],"72932":["US","72932","Cedarville","Arkansas","AR","Crawford","033","","","35.603","-94.3749","4"],"72934":["US","72934","Chester","Arkansas","AR","Crawford","033","","","35.6898","-94.202","4"],"72935":["US","72935","Dyer","Arkansas","AR","Crawford","033","","","35.4923","-94.1377","4"],"72946":["US","72946","Mountainburg","Arkansas","AR","Crawford","033","","","35.6464","-94.1497","4"],"72947":["US","72947","Mulberry","Arkansas","AR","Crawford","033","","","35.5172","-93.9885","4"],"72948":["US","72948","Natural Dam","Arkansas","AR","Crawford","033","","","35.6743","-94.4124","4"],"72952":["US","72952","Rudy","Arkansas","AR","Crawford","033","","","35.5468","-94.2913","4"],"72955":["US","72955","Uniontown","Arkansas","AR","Crawford","033","","","35.5748","-94.4349","4"],"72956":["US","72956","Van Buren","Arkansas","AR","Crawford","033","","","35.454","-94.3278","4"],"72957":["US","72957","Van Buren","Arkansas","AR","Crawford","033","","","35.4368","-94.3483","4"],"72301":["US","72301","West Memphis","Arkansas","AR","Crittenden","035","","","35.1484","-90.1779","4"],"72303":["US","72303","West Memphis","Arkansas","AR","Crittenden","035","","","35.1465","-90.1845","4"],"72325":["US","72325","Clarkedale","Arkansas","AR","Crittenden","035","","","35.3093","-90.2362","4"],"72327":["US","72327","Crawfordsville","Arkansas","AR","Crittenden","035","","","35.2119","-90.3351","4"],"72331":["US","72331","Earle","Arkansas","AR","Crittenden","035","","","35.2799","-90.4503","4"],"72332":["US","72332","Edmondson","Arkansas","AR","Crittenden","035","","","35.1042","-90.3133","4"],"72339":["US","72339","Gilmore","Arkansas","AR","Crittenden","035","","","35.4057","-90.2714","4"],"72364":["US","72364","Marion","Arkansas","AR","Crittenden","035","","","35.2077","-90.1989","4"],"72376":["US","72376","Proctor","Arkansas","AR","Crittenden","035","","","35.0834","-90.255","4"],"72384":["US","72384","Turrell","Arkansas","AR","Crittenden","035","","","35.3439","-90.2978","4"],"72324":["US","72324","Cherry Valley","Arkansas","AR","Cross","037","","","35.3991","-90.7613","4"],"72347":["US","72347","Hickory Ridge","Arkansas","AR","Cross","037","","","35.3995","-90.9823","4"],"72373":["US","72373","Parkin","Arkansas","AR","Cross","037","","","35.2586","-90.5564","4"],"72387":["US","72387","Vanndale","Arkansas","AR","Cross","037","","","35.3245","-90.7712","4"],"72396":["US","72396","Wynne","Arkansas","AR","Cross","037","","","35.233","-90.793","4"],"72379":["US","72379","Snow Lake","Arkansas","AR","Desha","041","","","34.0665","-91.0071","4"],"72032":["US","72032","Conway","Arkansas","AR","Faulkner","045","","","35.0842","-92.4236","4"],"72033":["US","72033","Conway","Arkansas","AR","Faulkner","045","","","35.1053","-92.3549","4"],"72034":["US","72034","Conway","Arkansas","AR","Faulkner","045","","","35.0823","-92.4683","4"],"72035":["US","72035","Conway","Arkansas","AR","Faulkner","045","","","35.1053","-92.3549","4"],"72039":["US","72039","Damascus","Arkansas","AR","Faulkner","045","","","35.3673","-92.4096","4"],"72047":["US","72047","Enola","Arkansas","AR","Faulkner","045","","","35.2087","-92.2123","4"],"72058":["US","72058","Greenbrier","Arkansas","AR","Faulkner","045","","","35.2295","-92.3578","4"],"72061":["US","72061","Guy","Arkansas","AR","Faulkner","045","","","35.3239","-92.2878","4"],"72106":["US","72106","Mayflower","Arkansas","AR","Faulkner","045","","","34.9669","-92.4001","4"],"72111":["US","72111","Mount Vernon","Arkansas","AR","Faulkner","045","","","35.2265","-92.124","4"],"72173":["US","72173","Vilonia","Arkansas","AR","Faulkner","045","","","35.0719","-92.1832","4"],"72181":["US","72181","Wooster","Arkansas","AR","Faulkner","045","","","35.1645","-92.453","4"],"72820":["US","72820","Alix","Arkansas","AR","Franklin","047","","","35.41","-93.7286","4"],"72821":["US","72821","Altus","Arkansas","AR","Franklin","047","","","35.4346","-93.7598","4"],"72928":["US","72928","Branch","Arkansas","AR","Franklin","047","","","35.2971","-93.9454","4"],"72930":["US","72930","Cecil","Arkansas","AR","Franklin","047","","","35.4252","-94.0409","4"],"72933":["US","72933","Charleston","Arkansas","AR","Franklin","047","","","35.3115","-94.0337","4"],"72949":["US","72949","Ozark","Arkansas","AR","Franklin","047","","","35.5246","-93.8374","4"],"72515":["US","72515","Bexar","Arkansas","AR","Fulton","049","","","36.2901","-92.055","4"],"72520":["US","72520","Camp","Arkansas","AR","Fulton","049","","","36.4025","-91.7262","4"],"72531":["US","72531","Elizabeth","Arkansas","AR","Fulton","049","","","36.3238","-92.0934","4"],"72538":["US","72538","Gepp","Arkansas","AR","Fulton","049","","","36.4364","-92.0995","4"],"72539":["US","72539","Glencoe","Arkansas","AR","Fulton","049","","","36.2942","-91.7474","4"],"72554":["US","72554","Mammoth Spring","Arkansas","AR","Fulton","049","","","36.4076","-91.5757","4"],"72576":["US","72576","Salem","Arkansas","AR","Fulton","049","","","36.3766","-91.8759","4"],"72578":["US","72578","Sturkie","Arkansas","AR","Fulton","049","","","36.4747","-91.8891","4"],"72583":["US","72583","Viola","Arkansas","AR","Fulton","049","","","36.3924","-91.9932","4"],"72087":["US","72087","Lonsdale","Arkansas","AR","Garland","051","","","34.5562","-92.834","4"],"72057":["US","72057","Grapevine","Arkansas","AR","Grant","053","","","34.1309","-92.3109","4"],"72084":["US","72084","Leola","Arkansas","AR","Grant","053","","","34.1856","-92.5979","4"],"72128":["US","72128","Poyen","Arkansas","AR","Grant","053","","","34.3023","-92.6095","4"],"72129":["US","72129","Prattsville","Arkansas","AR","Grant","053","","","34.3079","-92.5131","4"],"72150":["US","72150","Sheridan","Arkansas","AR","Grant","053","","","34.3165","-92.3657","4"],"72412":["US","72412","Beech Grove","Arkansas","AR","Greene","055","","","36.1281","-90.6914","4"],"72425":["US","72425","Delaplaine","Arkansas","AR","Greene","055","","","36.1995","-90.7345","4"],"72436":["US","72436","Lafe","Arkansas","AR","Greene","055","","","36.2359","-90.4811","4"],"72443":["US","72443","Marmaduke","Arkansas","AR","Greene","055","","","36.1951","-90.3837","4"],"72450":["US","72450","Paragould","Arkansas","AR","Greene","055","","","36.06","-90.5251","4"],"72451":["US","72451","Paragould","Arkansas","AR","Greene","055","","","36.0584","-90.4973","4"],"72474":["US","72474","Walcott","Arkansas","AR","Greene","055","","","36.0413","-90.6718","4"],"72019":["US","72019","Benton","Arkansas","AR","Hot Spring","059","","","34.604","-92.6259","4"],"72104":["US","72104","Malvern","Arkansas","AR","Hot Spring","059","","","34.3557","-92.8292","4"],"72105":["US","72105","Jones Mill","Arkansas","AR","Hot Spring","059","","","34.4374","-92.8943","1"],"72165":["US","72165","Thida","Arkansas","AR","Independence","063","","","35.5762","-91.4539","4"],"72501":["US","72501","Batesville","Arkansas","AR","Independence","063","","","35.7826","-91.6352","4"],"72503":["US","72503","Batesville","Arkansas","AR","Independence","063","","","35.7346","-91.5343","4"],"72522":["US","72522","Charlotte","Arkansas","AR","Independence","063","","","35.8184","-91.4387","4"],"72524":["US","72524","Cord","Arkansas","AR","Independence","063","","","35.8184","-91.3375","4"],"72526":["US","72526","Cushman","Arkansas","AR","Independence","063","","","35.8729","-91.754","4"],"72527":["US","72527","Desha","Arkansas","AR","Independence","063","","","35.7411","-91.6985","4"],"72534":["US","72534","Floral","Arkansas","AR","Independence","063","","","35.6023","-91.7341","4"],"72550":["US","72550","Locust Grove","Arkansas","AR","Independence","063","","","35.7177","-91.7414","4"],"72553":["US","72553","Magness","Arkansas","AR","Independence","063","","","35.6941","-91.4753","4"],"72562":["US","72562","Newark","Arkansas","AR","Independence","063","","","35.7118","-91.4394","4"],"72564":["US","72564","Oil Trough","Arkansas","AR","Independence","063","","","35.6131","-91.4703","4"],"72568":["US","72568","Pleasant Plains","Arkansas","AR","Independence","063","","","35.5893","-91.632","4"],"72571":["US","72571","Rosie","Arkansas","AR","Independence","063","","","35.6638","-91.534","4"],"72575":["US","72575","Salado","Arkansas","AR","Independence","063","","","35.6919","-91.5989","4"],"72579":["US","72579","Sulphur Rock","Arkansas","AR","Independence","063","","","35.7545","-91.5073","4"],"72512":["US","72512","Horseshoe Bend","Arkansas","AR","Izard","065","","","36.2025","-91.7553","4"],"72517":["US","72517","Brockwell","Arkansas","AR","Izard","065","","","36.1358","-91.9513","4"],"72519":["US","72519","Calico Rock","Arkansas","AR","Izard","065","","","36.1202","-92.1867","4"],"72528":["US","72528","Dolph","Arkansas","AR","Izard","065","","","36.2229","-92.1177","4"],"72536":["US","72536","Franklin","Arkansas","AR","Izard","065","","","36.1703","-91.776","4"],"72540":["US","72540","Guion","Arkansas","AR","Izard","065","","","35.9266","-91.9103","4"],"72556":["US","72556","Melbourne","Arkansas","AR","Izard","065","","","36.0635","-91.9079","4"],"72561":["US","72561","Mount Pleasant","Arkansas","AR","Izard","065","","","35.9759","-91.785","4"],"72565":["US","72565","Oxford","Arkansas","AR","Izard","065","","","36.2114","-91.9258","4"],"72566":["US","72566","Pineville","Arkansas","AR","Izard","065","","","36.1677","-92.1073","4"],"72573":["US","72573","Sage","Arkansas","AR","Izard","065","","","36.0688","-91.791","4"],"72584":["US","72584","Violet Hill","Arkansas","AR","Izard","065","","","36.163","-91.8471","4"],"72585":["US","72585","Wideman","Arkansas","AR","Izard","065","","","36.1865","-92.0088","4"],"72587":["US","72587","Wiseman","Arkansas","AR","Izard","065","","","36.2345","-91.8154","4"],"72005":["US","72005","Amagon","Arkansas","AR","Jackson","067","","","35.562","-91.1104","4"],"72014":["US","72014","Beedeville","Arkansas","AR","Jackson","067","","","35.4291","-91.1057","4"],"72043":["US","72043","Diaz","Arkansas","AR","Jackson","067","","","35.6336","-91.2592","4"],"72075":["US","72075","Jacksonport","Arkansas","AR","Jackson","067","","","35.6414","-91.3072","4"],"72112":["US","72112","Newport","Arkansas","AR","Jackson","067","","","35.5988","-91.2571","4"],"72169":["US","72169","Tupelo","Arkansas","AR","Jackson","067","","","35.3844","-91.2232","4"],"72431":["US","72431","Grubbs","Arkansas","AR","Jackson","067","","","35.6498","-91.074","4"],"72471":["US","72471","Swifton","Arkansas","AR","Jackson","067","","","35.8274","-91.1264","4"],"72473":["US","72473","Tuckerman","Arkansas","AR","Jackson","067","","","35.7307","-91.2003","4"],"72004":["US","72004","Altheimer","Arkansas","AR","Jefferson","069","","","34.3062","-91.8289","4"],"72079":["US","72079","Jefferson","Arkansas","AR","Jefferson","069","","","34.3934","-92.2029","4"],"72132":["US","72132","Redfield","Arkansas","AR","Jefferson","069","","","34.4526","-92.1758","4"],"72133":["US","72133","Reydell","Arkansas","AR","Jefferson","069","","","34.1715","-91.5656","4"],"72152":["US","72152","Sherrill","Arkansas","AR","Jefferson","069","","","34.3581","-91.9933","4"],"72168":["US","72168","Tucker","Arkansas","AR","Jefferson","069","","","34.4414","-91.9163","4"],"72175":["US","72175","Wabbaseka","Arkansas","AR","Jefferson","069","","","34.3936","-91.7549","4"],"72182":["US","72182","Wright","Arkansas","AR","Jefferson","069","","","34.4291","-92.0599","4"],"72830":["US","72830","Clarksville","Arkansas","AR","Johnson","071","","","35.4908","-93.4911","4"],"72832":["US","72832","Coal Hill","Arkansas","AR","Johnson","071","","","35.4371","-93.672","4"],"72839":["US","72839","Hagarville","Arkansas","AR","Johnson","071","","","35.6155","-93.2726","4"],"72840":["US","72840","Hartman","Arkansas","AR","Johnson","071","","","35.4436","-93.6142","4"],"72845":["US","72845","Knoxville","Arkansas","AR","Johnson","071","","","35.3749","-93.3618","4"],"72846":["US","72846","Lamar","Arkansas","AR","Johnson","071","","","35.4349","-93.3552","4"],"72852":["US","72852","Oark","Arkansas","AR","Johnson","071","","","35.7095","-93.5585","4"],"72854":["US","72854","Ozone","Arkansas","AR","Johnson","071","","","35.6575","-93.4311","4"],"72410":["US","72410","Alicia","Arkansas","AR","Lawrence","075","","","35.9423","-91.081","4"],"72415":["US","72415","Black Rock","Arkansas","AR","Lawrence","075","","","36.1149","-91.1176","4"],"72433":["US","72433","Hoxie","Arkansas","AR","Lawrence","075","","","36.0326","-90.9715","4"],"72434":["US","72434","Imboden","Arkansas","AR","Lawrence","075","","","36.1976","-91.1854","4"],"72440":["US","72440","Lynn","Arkansas","AR","Lawrence","075","","","35.9813","-91.2676","4"],"72445":["US","72445","Minturn","Arkansas","AR","Lawrence","075","","","35.9728","-91.0235","4"],"72457":["US","72457","Portia","Arkansas","AR","Lawrence","075","","","36.0865","-91.0673","4"],"72458":["US","72458","Powhatan","Arkansas","AR","Lawrence","075","","","36.08","-91.1482","4"],"72459":["US","72459","Ravenden","Arkansas","AR","Lawrence","075","","","36.2029","-91.2593","4"],"72465":["US","72465","Sedgwick","Arkansas","AR","Lawrence","075","","","35.9643","-90.8954","4"],"72466":["US","72466","Smithville","Arkansas","AR","Lawrence","075","","","36.0908","-91.2745","4"],"72469":["US","72469","Strawberry","Arkansas","AR","Lawrence","075","","","35.9673","-91.2935","4"],"72476":["US","72476","Walnut Ridge","Arkansas","AR","Lawrence","075","","","36.0244","-90.9288","4"],"72572":["US","72572","Saffell","Arkansas","AR","Lawrence","075","","","35.8781","-91.3004","4"],"72311":["US","72311","Aubrey","Arkansas","AR","Lee","077","","","34.7195","-90.8969","4"],"72320":["US","72320","Brickeys","Arkansas","AR","Lee","077","","","34.8548","-90.5377","4"],"72341":["US","72341","Haynes","Arkansas","AR","Lee","077","","","34.8838","-90.7666","4"],"72352":["US","72352","La Grange","Arkansas","AR","Lee","077","","","34.7697","-90.7552","4"],"72360":["US","72360","Marianna","Arkansas","AR","Lee","077","","","34.7759","-90.7785","4"],"72368":["US","72368","Moro","Arkansas","AR","Lee","077","","","34.803","-91.006","4"],"72826":["US","72826","Blue Mountain","Arkansas","AR","Logan","083","","","35.1602","-93.6183","4"],"72835":["US","72835","Delaware","Arkansas","AR","Logan","083","","","35.278","-93.3462","4"],"72851":["US","72851","New Blaine","Arkansas","AR","Logan","083","","","35.3189","-93.4446","4"],"72855":["US","72855","Paris","Arkansas","AR","Logan","083","","","35.2941","-93.7265","4"],"72863":["US","72863","Scranton","Arkansas","AR","Logan","083","","","35.3585","-93.5454","4"],"72865":["US","72865","Subiaco","Arkansas","AR","Logan","083","","","35.3153","-93.5991","4"],"72927":["US","72927","Booneville","Arkansas","AR","Logan","083","","","35.1364","-93.9274","4"],"72943":["US","72943","Magazine","Arkansas","AR","Logan","083","","","35.1587","-93.8003","4"],"72951":["US","72951","Ratcliff","Arkansas","AR","Logan","083","","","35.2917","-93.8899","4"],"72007":["US","72007","Austin","Arkansas","AR","Lonoke","085","","","34.9921","-91.9798","4"],"72023":["US","72023","Cabot","Arkansas","AR","Lonoke","085","","","34.9457","-92.0318","4"],"72024":["US","72024","Carlisle","Arkansas","AR","Lonoke","085","","","34.7933","-91.7459","4"],"72037":["US","72037","Coy","Arkansas","AR","Lonoke","085","","","34.5387","-91.874","4"],"72046":["US","72046","England","Arkansas","AR","Lonoke","085","","","34.5575","-91.9484","4"],"72072":["US","72072","Humnoke","Arkansas","AR","Lonoke","085","","","34.4857","-91.7624","4"],"72083":["US","72083","Keo","Arkansas","AR","Lonoke","085","","","34.6041","-92.0078","4"],"72086":["US","72086","Lonoke","Arkansas","AR","Lonoke","085","","","34.7832","-91.9214","4"],"72176":["US","72176","Ward","Arkansas","AR","Lonoke","085","","","34.9532","-91.9004","4"],"72721":["US","72721","Combs","Arkansas","AR","Madison","087","","","35.8607","-93.8112","4"],"72738":["US","72738","Hindsville","Arkansas","AR","Madison","087","","","36.1422","-93.8633","4"],"72740":["US","72740","Huntsville","Arkansas","AR","Madison","087","","","36.1043","-93.7279","4"],"72742":["US","72742","Kingston","Arkansas","AR","Madison","087","","","36.0485","-93.5044","4"],"72752":["US","72752","Pettigrew","Arkansas","AR","Madison","087","","","35.8346","-93.6181","4"],"72760":["US","72760","Saint Paul","Arkansas","AR","Madison","087","","","35.8496","-93.7347","4"],"72773":["US","72773","Wesley","Arkansas","AR","Madison","087","","","36.0114","-93.8526","4"],"72776":["US","72776","Witter","Arkansas","AR","Madison","087","","","35.9356","-93.621","4"],"72619":["US","72619","Bull Shoals","Arkansas","AR","Marion","089","","","36.371","-92.5938","4"],"72634":["US","72634","Flippin","Arkansas","AR","Marion","089","","","36.2682","-92.578","4"],"72661":["US","72661","Oakland","Arkansas","AR","Marion","089","","","36.4442","-92.5832","4"],"72668":["US","72668","Peel","Arkansas","AR","Marion","089","","","36.435","-92.7615","4"],"72672":["US","72672","Pyatt","Arkansas","AR","Marion","089","","","36.2486","-92.8416","4"],"72677":["US","72677","Summit","Arkansas","AR","Marion","089","","","36.2523","-92.6907","4"],"72687":["US","72687","Yellville","Arkansas","AR","Marion","089","","","36.2253","-92.7245","4"],"72310":["US","72310","Armorel","Arkansas","AR","Mississippi","093","","","35.9201","-89.7981","4"],"72313":["US","72313","Bassett","Arkansas","AR","Mississippi","093","","","35.5365","-90.1268","4"],"72315":["US","72315","Blytheville","Arkansas","AR","Mississippi","093","","","35.9273","-89.919","4"],"72316":["US","72316","Blytheville","Arkansas","AR","Mississippi","093","","","35.9273","-89.919","4"],"72319":["US","72319","Gosnell","Arkansas","AR","Mississippi","093","","","35.9598","-89.972","4"],"72321":["US","72321","Burdette","Arkansas","AR","Mississippi","093","","","35.8173","-89.9393","4"],"72329":["US","72329","Driver","Arkansas","AR","Mississippi","093","","","35.6253","-90.0138","4"],"72330":["US","72330","Dyess","Arkansas","AR","Mississippi","093","","","35.5954","-90.2157","4"],"72338":["US","72338","Frenchmans Bayou","Arkansas","AR","Mississippi","093","","","35.4591","-90.1884","4"],"72350":["US","72350","Joiner","Arkansas","AR","Mississippi","093","","","35.5052","-90.1478","4"],"72351":["US","72351","Keiser","Arkansas","AR","Mississippi","093","","","35.6737","-90.0963","4"],"72358":["US","72358","Luxora","Arkansas","AR","Mississippi","093","","","35.7608","-89.922","4"],"72370":["US","72370","Osceola","Arkansas","AR","Mississippi","093","","","35.7019","-89.9798","4"],"72391":["US","72391","West Ridge","Arkansas","AR","Mississippi","093","","","35.6831","-90.2626","4"],"72395":["US","72395","Wilson","Arkansas","AR","Mississippi","093","","","35.566","-90.0427","4"],"72426":["US","72426","Dell","Arkansas","AR","Mississippi","093","","","35.8554","-90.0418","4"],"72428":["US","72428","Etowah","Arkansas","AR","Mississippi","093","","","35.7337","-90.1838","4"],"72438":["US","72438","Leachville","Arkansas","AR","Mississippi","093","","","35.9332","-90.1955","4"],"72442":["US","72442","Manila","Arkansas","AR","Mississippi","093","","","35.8439","-90.1806","4"],"72021":["US","72021","Brinkley","Arkansas","AR","Monroe","095","","","34.8781","-91.1886","4"],"72029":["US","72029","Clarendon","Arkansas","AR","Monroe","095","","","34.6601","-91.2564","4"],"72069":["US","72069","Holly Grove","Arkansas","AR","Monroe","095","","","34.5993","-91.1844","4"],"72108":["US","72108","Monroe","Arkansas","AR","Monroe","095","","","34.7348","-91.1046","4"],"72134":["US","72134","Roe","Arkansas","AR","Monroe","095","","","34.6286","-91.3771","4"],"72624":["US","72624","Compton","Arkansas","AR","Newton","101","","","36.0979","-93.3099","4"],"72628":["US","72628","Deer","Arkansas","AR","Newton","101","","","35.853","-93.3174","4"],"72640":["US","72640","Hasty","Arkansas","AR","Newton","101","","","36.0152","-93.046","4"],"72641":["US","72641","Jasper","Arkansas","AR","Newton","101","","","36.0038","-93.2048","4"],"72648":["US","72648","Marble Falls","Arkansas","AR","Newton","101","","","36.0695","-93.1566","4"],"72655":["US","72655","Mount Judea","Arkansas","AR","Newton","101","","","35.9407","-93.0654","4"],"72666":["US","72666","Parthenon","Arkansas","AR","Newton","101","","","35.9451","-93.2677","4"],"72670":["US","72670","Ponca","Arkansas","AR","Newton","101","","","36.0242","-93.3646","4"],"72683":["US","72683","Vendor","Arkansas","AR","Newton","101","","","35.9473","-93.0774","4"],"72685":["US","72685","Western Grove","Arkansas","AR","Newton","101","","","36.083","-92.9716","4"],"72001":["US","72001","Adona","Arkansas","AR","Perry","105","","","35.047","-92.9033","4"],"72016":["US","72016","Bigelow","Arkansas","AR","Perry","105","","","34.9847","-92.6308","4"],"72025":["US","72025","Casa","Arkansas","AR","Perry","105","","","35.0322","-93.047","4"],"72070":["US","72070","Houston","Arkansas","AR","Perry","105","","","35.0362","-92.6913","4"],"72125":["US","72125","Perry","Arkansas","AR","Perry","105","","","35.0443","-92.7958","4"],"72126":["US","72126","Perryville","Arkansas","AR","Perry","105","","","34.9701","-92.8472","4"],"72312":["US","72312","Barton","Arkansas","AR","Phillips","107","","","34.5467","-90.7679","4"],"72328":["US","72328","Crumrod","Arkansas","AR","Phillips","107","","","34.1335","-90.9751","4"],"72333":["US","72333","Elaine","Arkansas","AR","Phillips","107","","","34.3118","-90.8939","4"],"72342":["US","72342","Helena","Arkansas","AR","Phillips","107","","","34.5325","-90.6298","4"],"72353":["US","72353","Lambrook","Arkansas","AR","Phillips","107","","","34.3286","-90.9652","4"],"72355":["US","72355","Lexa","Arkansas","AR","Phillips","107","","","34.5979","-90.7523","4"],"72366":["US","72366","Marvell","Arkansas","AR","Phillips","107","","","34.5485","-90.9413","4"],"72367":["US","72367","Mellwood","Arkansas","AR","Phillips","107","","","34.2198","-90.9504","4"],"72369":["US","72369","Oneida","Arkansas","AR","Phillips","107","","","34.4542","-90.7684","4"],"72374":["US","72374","Poplar Grove","Arkansas","AR","Phillips","107","","","34.5394","-90.8813","4"],"72383":["US","72383","Turner","Arkansas","AR","Phillips","107","","","34.4762","-91.0187","4"],"72389":["US","72389","Wabash","Arkansas","AR","Phillips","107","","","34.3466","-90.8869","4"],"72390":["US","72390","West Helena","Arkansas","AR","Phillips","107","","","34.5496","-90.6545","4"],"72354":["US","72354","Lepanto","Arkansas","AR","Poinsett","111","","","35.6069","-90.3359","4"],"72365":["US","72365","Marked Tree","Arkansas","AR","Poinsett","111","","","35.5349","-90.4194","4"],"72377":["US","72377","Rivervale","Arkansas","AR","Poinsett","111","","","35.674","-90.3401","4"],"72386":["US","72386","Tyronza","Arkansas","AR","Poinsett","111","","","35.4865","-90.3519","4"],"72429":["US","72429","Fisher","Arkansas","AR","Poinsett","111","","","35.514","-90.955","4"],"72432":["US","72432","Harrisburg","Arkansas","AR","Poinsett","111","","","35.5722","-90.7038","4"],"72472":["US","72472","Trumann","Arkansas","AR","Poinsett","111","","","35.5882","-90.562","4"],"72475":["US","72475","Waldenburg","Arkansas","AR","Poinsett","111","","","35.5631","-90.9207","4"],"72479":["US","72479","Weiner","Arkansas","AR","Poinsett","111","","","35.6291","-90.9289","4"],"72679":["US","72679","Tilly","Arkansas","AR","Pope","115","","","35.7341","-92.8391","4"],"72801":["US","72801","Russellville","Arkansas","AR","Pope","115","","","35.2842","-93.1315","4"],"72802":["US","72802","Russellville","Arkansas","AR","Pope","115","","","35.3067","-93.0712","4"],"72811":["US","72811","Russellville","Arkansas","AR","Pope","115","","","35.2784","-93.1338","4"],"72812":["US","72812","Russellville","Arkansas","AR","Pope","115","","","35.4231","-93.0544","4"],"72823":["US","72823","Atkins","Arkansas","AR","Pope","115","","","35.2449","-92.9507","4"],"72837":["US","72837","Dover","Arkansas","AR","Pope","115","","","35.4074","-93.1355","4"],"72843":["US","72843","Hector","Arkansas","AR","Pope","115","","","35.5499","-92.9616","4"],"72847":["US","72847","London","Arkansas","AR","Pope","115","","","35.3744","-93.2736","4"],"72856":["US","72856","Pelsor","Arkansas","AR","Pope","115","","","35.7854","-93.0812","4"],"72858":["US","72858","Pottsville","Arkansas","AR","Pope","115","","","35.2398","-93.0564","4"],"72017":["US","72017","Biscoe","Arkansas","AR","Prairie","117","","","34.8733","-91.3945","4"],"72040":["US","72040","Des Arc","Arkansas","AR","Prairie","117","","","34.9751","-91.5113","4"],"72041":["US","72041","De Valls Bluff","Arkansas","AR","Prairie","117","","","34.7447","-91.4982","4"],"72064":["US","72064","Hazen","Arkansas","AR","Prairie","117","","","34.7838","-91.5767","4"],"72066":["US","72066","Hickory Plains","Arkansas","AR","Prairie","117","","","34.9901","-91.7368","4"],"72170":["US","72170","Ulm","Arkansas","AR","Prairie","117","","","34.5772","-91.4633","4"],"72002":["US","72002","Alexander","Arkansas","AR","Pulaski","119","","","34.6313","-92.4727","4"],"72053":["US","72053","College Station","Arkansas","AR","Pulaski","119","","","34.7093","-92.2283","4"],"72065":["US","72065","Hensley","Arkansas","AR","Pulaski","119","","","34.5208","-92.2758","4"],"72076":["US","72076","Jacksonville","Arkansas","AR","Pulaski","119","","","34.919","-92.1419","4"],"72078":["US","72078","Jacksonville","Arkansas","AR","Pulaski","119","","","34.8662","-92.1101","4"],"72099":["US","72099","Little Rock Air Force Base","Arkansas","AR","Pulaski","119","","","34.9074","-92.1397","4"],"72103":["US","72103","Mabelvale","Arkansas","AR","Pulaski","119","","","34.6478","-92.3849","4"],"72113":["US","72113","Maumelle","Arkansas","AR","Pulaski","119","","","34.8491","-92.4059","4"],"72114":["US","72114","North Little Rock","Arkansas","AR","Pulaski","119","","","34.7666","-92.2629","4"],"72115":["US","72115","North Little Rock","Arkansas","AR","Pulaski","119","","","34.7695","-92.2671","4"],"72116":["US","72116","North Little Rock","Arkansas","AR","Pulaski","119","","","34.8059","-92.2305","4"],"72117":["US","72117","North Little Rock","Arkansas","AR","Pulaski","119","","","34.7658","-92.1524","4"],"72118":["US","72118","North Little Rock","Arkansas","AR","Pulaski","119","","","34.8337","-92.3289","4"],"72119":["US","72119","North Little Rock","Arkansas","AR","Pulaski","119","","","34.8017","-92.2598","4"],"72120":["US","72120","Sherwood","Arkansas","AR","Pulaski","119","","","34.8807","-92.2303","4"],"72124":["US","72124","North Little Rock","Arkansas","AR","Pulaski","119","","","34.7519","-92.3925","4"],"72135":["US","72135","Roland","Arkansas","AR","Pulaski","119","","","34.8829","-92.5192","4"],"72142":["US","72142","Scott","Arkansas","AR","Pulaski","119","","","34.6942","-92.1157","4"],"72164":["US","72164","Sweet Home","Arkansas","AR","Pulaski","119","","","34.6873","-92.2399","4"],"72180":["US","72180","Woodson","Arkansas","AR","Pulaski","119","","","34.5338","-92.2089","4"],"72183":["US","72183","Wrightsville","Arkansas","AR","Pulaski","119","","","34.6012","-92.1938","4"],"72190":["US","72190","North Little Rock","Arkansas","AR","Pulaski","119","","","34.7519","-92.3925","4"],"72199":["US","72199","North Little Rock","Arkansas","AR","Pulaski","119","","","34.8272","-92.2847","4"],"72201":["US","72201","Little Rock","Arkansas","AR","Pulaski","119","","","34.7483","-92.2819","4"],"72202":["US","72202","Little Rock","Arkansas","AR","Pulaski","119","","","34.7363","-92.2741","4"],"72203":["US","72203","Little Rock","Arkansas","AR","Pulaski","119","","","34.8835","-92.3908","4"],"72204":["US","72204","Little Rock","Arkansas","AR","Pulaski","119","","","34.7269","-92.344","4"],"72205":["US","72205","Little Rock","Arkansas","AR","Pulaski","119","","","34.751","-92.3455","4"],"72206":["US","72206","Little Rock","Arkansas","AR","Pulaski","119","","","34.6836","-92.2776","4"],"72207":["US","72207","Little Rock","Arkansas","AR","Pulaski","119","","","34.7721","-92.3565","4"],"72209":["US","72209","Little Rock","Arkansas","AR","Pulaski","119","","","34.6725","-92.3529","4"],"72210":["US","72210","Little Rock","Arkansas","AR","Pulaski","119","","","34.7076","-92.466","4"],"72211":["US","72211","Little Rock","Arkansas","AR","Pulaski","119","","","34.7413","-92.4222","4"],"72212":["US","72212","Little Rock","Arkansas","AR","Pulaski","119","","","34.7871","-92.4222","4"],"72214":["US","72214","Little Rock","Arkansas","AR","Pulaski","119","","","34.7621","-92.2282","4"],"72215":["US","72215","Little Rock","Arkansas","AR","Pulaski","119","","","34.7519","-92.3925","4"],"72216":["US","72216","Little Rock","Arkansas","AR","Pulaski","119","","","34.8178","-92.2357","4"],"72217":["US","72217","Little Rock","Arkansas","AR","Pulaski","119","","","34.8302","-92.1702","4"],"72219":["US","72219","Little Rock","Arkansas","AR","Pulaski","119","","","34.7519","-92.3925","4"],"72221":["US","72221","Little Rock","Arkansas","AR","Pulaski","119","","","34.7519","-92.3925","4"],"72222":["US","72222","Little Rock","Arkansas","AR","Pulaski","119","","","34.7519","-92.3925","4"],"72223":["US","72223","Little Rock","Arkansas","AR","Pulaski","119","","","34.7902","-92.5044","4"],"72225":["US","72225","Little Rock","Arkansas","AR","Pulaski","119","","","34.7519","-92.3925","4"],"72227":["US","72227","Little Rock","Arkansas","AR","Pulaski","119","","","34.7757","-92.3724","4"],"72231":["US","72231","Little Rock","Arkansas","AR","Pulaski","119","","","34.8019","-92.1894","4"],"72295":["US","72295","Little Rock","Arkansas","AR","Pulaski","119","","","34.7519","-92.3925","4"],"72413":["US","72413","Biggers","Arkansas","AR","Randolph","121","","","36.2844","-90.8538","4"],"72444":["US","72444","Maynard","Arkansas","AR","Randolph","121","","","36.4386","-90.8749","4"],"72449":["US","72449","O Kean","Arkansas","AR","Randolph","121","","","36.1797","-90.8241","4"],"72455":["US","72455","Pocahontas","Arkansas","AR","Randolph","121","","","36.2829","-90.9968","4"],"72460":["US","72460","Ravenden Springs","Arkansas","AR","Randolph","121","","","36.3104","-91.2094","4"],"72462":["US","72462","Reyno","Arkansas","AR","Randolph","121","","","36.3744","-90.7676","4"],"72478":["US","72478","Warm Springs","Arkansas","AR","Randolph","121","","","36.4803","-91.0515","4"],"72322":["US","72322","Caldwell","Arkansas","AR","St. Francis","123","","","35.0562","-90.8288","4"],"72326":["US","72326","Colt","Arkansas","AR","St. Francis","123","","","35.0881","-90.8895","4"],"72335":["US","72335","Forrest City","Arkansas","AR","St. Francis","123","","","35.0091","-90.7886","4"],"72336":["US","72336","Forrest City","Arkansas","AR","St. Francis","123","","","35.0081","-90.7898","4"],"72340":["US","72340","Goodwin","Arkansas","AR","St. Francis","123","","","34.9358","-91.0292","4"],"72346":["US","72346","Heth","Arkansas","AR","St. Francis","123","","","35.0973","-90.4586","4"],"72348":["US","72348","Hughes","Arkansas","AR","St. Francis","123","","","34.9454","-90.4741","4"],"72359":["US","72359","Madison","Arkansas","AR","St. Francis","123","","","35.0252","-90.7086","4"],"72372":["US","72372","Palestine","Arkansas","AR","St. Francis","123","","","34.9663","-90.9049","4"],"72392":["US","72392","Wheatley","Arkansas","AR","St. Francis","123","","","34.9207","-91.1086","4"],"72394":["US","72394","Widener","Arkansas","AR","St. Francis","123","","","35.0592","-90.6293","4"],"72011":["US","72011","Bauxite","Arkansas","AR","Saline","125","","","34.5091","-92.4828","4"],"72015":["US","72015","Benton","Arkansas","AR","Saline","125","","","34.4933","-92.5896","4"],"72018":["US","72018","Benton","Arkansas","AR","Saline","125","","","34.5645","-92.5868","4"],"72022":["US","72022","Bryant","Arkansas","AR","Saline","125","","","34.6068","-92.492","4"],"72089":["US","72089","Bryant","Arkansas","AR","Saline","125","","","34.5959","-92.489","4"],"72122":["US","72122","Paron","Arkansas","AR","Saline","125","","","34.7853","-92.7482","4"],"72158":["US","72158","Benton","Arkansas","AR","Saline","125","","","34.635","-92.6597","4"],"72167":["US","72167","Traskwood","Arkansas","AR","Saline","125","","","34.4508","-92.6547","4"],"72841":["US","72841","Harvey","Arkansas","AR","Scott","127","","","34.8762","-93.764","4"],"72926":["US","72926","Boles","Arkansas","AR","Scott","127","","","34.7654","-94.0629","4"],"72944":["US","72944","Mansfield","Arkansas","AR","Scott","127","","","35.0432","-94.2204","4"],"72950":["US","72950","Parks","Arkansas","AR","Scott","127","","","34.8003","-93.9509","4"],"72958":["US","72958","Waldron","Arkansas","AR","Scott","127","","","34.9026","-94.0772","4"],"72636":["US","72636","Gilbert","Arkansas","AR","Searcy","129","","","35.9879","-92.7163","4"],"72639":["US","72639","Harriet","Arkansas","AR","Searcy","129","","","35.9991","-92.5042","4"],"72645":["US","72645","Leslie","Arkansas","AR","Searcy","129","","","35.8272","-92.5663","4"],"72650":["US","72650","Marshall","Arkansas","AR","Searcy","129","","","35.9267","-92.6402","4"],"72669":["US","72669","Pindall","Arkansas","AR","Searcy","129","","","36.0675","-92.8864","4"],"72675":["US","72675","Saint Joe","Arkansas","AR","Searcy","129","","","35.9877","-92.7928","4"],"72686":["US","72686","Witts Springs","Arkansas","AR","Searcy","129","","","35.7681","-92.8668","4"],"72901":["US","72901","Fort Smith","Arkansas","AR","Sebastian","131","","","35.3653","-94.411","4"],"72902":["US","72902","Fort Smith","Arkansas","AR","Sebastian","131","","","35.3862","-94.4091","4"],"72903":["US","72903","Fort Smith","Arkansas","AR","Sebastian","131","","","35.3427","-94.3784","4"],"72904":["US","72904","Fort Smith","Arkansas","AR","Sebastian","131","","","35.4051","-94.3872","4"],"72905":["US","72905","Fort Smith","Arkansas","AR","Sebastian","131","","","35.3859","-94.3985","4"],"72906":["US","72906","Fort Smith","Arkansas","AR","Sebastian","131","","","35.3859","-94.3985","4"],"72908":["US","72908","Fort Smith","Arkansas","AR","Sebastian","131","","","35.3219","-94.4028","4"],"72913":["US","72913","Fort Smith","Arkansas","AR","Sebastian","131","","","35.3859","-94.3985","4"],"72914":["US","72914","Fort Smith","Arkansas","AR","Sebastian","131","","","35.3859","-94.3985","4"],"72916":["US","72916","Fort Smith","Arkansas","AR","Sebastian","131","","","35.2502","-94.3703","4"],"72917":["US","72917","Fort Smith","Arkansas","AR","Sebastian","131","","","35.3859","-94.3985","4"],"72918":["US","72918","Fort Smith","Arkansas","AR","Sebastian","131","","","35.3859","-94.3985","4"],"72919":["US","72919","Fort Smith","Arkansas","AR","Sebastian","131","","","35.3859","-94.3985","4"],"72923":["US","72923","Barling","Arkansas","AR","Sebastian","131","","","35.333","-94.3082","4"],"72936":["US","72936","Greenwood","Arkansas","AR","Sebastian","131","","","35.1955","-94.253","4"],"72937":["US","72937","Hackett","Arkansas","AR","Sebastian","131","","","35.1945","-94.3983","4"],"72938":["US","72938","Hartford","Arkansas","AR","Sebastian","131","","","35.0222","-94.3819","4"],"72940":["US","72940","Huntington","Arkansas","AR","Sebastian","131","","","35.0963","-94.3313","4"],"72941":["US","72941","Lavaca","Arkansas","AR","Sebastian","131","","","35.3661","-94.1917","4"],"72945":["US","72945","Midland","Arkansas","AR","Sebastian","131","","","35.0932","-94.3533","4"],"72482":["US","72482","Williford","Arkansas","AR","Sharp","135","","","36.2453","-91.3792","4"],"72513":["US","72513","Ash Flat","Arkansas","AR","Sharp","135","","","36.2201","-91.6421","4"],"72521":["US","72521","Cave City","Arkansas","AR","Sharp","135","","","35.9517","-91.5444","4"],"72525":["US","72525","Cherokee Village","Arkansas","AR","Sharp","135","","","36.311","-91.597","4"],"72529":["US","72529","Cherokee Village","Arkansas","AR","Sharp","135","","","36.3011","-91.5281","4"],"72532":["US","72532","Evening Shade","Arkansas","AR","Sharp","135","","","36.0855","-91.598","4"],"72542":["US","72542","Hardy","Arkansas","AR","Sharp","135","","","36.3227","-91.411","4"],"72569":["US","72569","Poughkeepsie","Arkansas","AR","Sharp","135","","","36.0767","-91.4793","4"],"72577":["US","72577","Sidney","Arkansas","AR","Sharp","135","","","36.0664","-91.642","4"],"72051":["US","72051","Fox","Arkansas","AR","Stone","137","","","35.7682","-92.3043","4"],"72533":["US","72533","Fifty Six","Arkansas","AR","Stone","137","","","35.992","-92.2182","4"],"72555":["US","72555","Marcella","Arkansas","AR","Stone","137","","","35.7756","-91.8718","4"],"72560":["US","72560","Mountain View","Arkansas","AR","Stone","137","","","35.8208","-92.0389","4"],"72567":["US","72567","Pleasant Grove","Arkansas","AR","Stone","137","","","35.8265","-91.8958","4"],"72657":["US","72657","Timbo","Arkansas","AR","Stone","137","","","35.919","-92.1272","4"],"72663":["US","72663","Onia","Arkansas","AR","Stone","137","","","35.9403","-92.3459","4"],"72680":["US","72680","Timbo","Arkansas","AR","Stone","137","","","35.8845","-92.2913","4"],"72013":["US","72013","Bee Branch","Arkansas","AR","Van Buren","141","","","35.4683","-92.3779","4"],"72028":["US","72028","Choctaw","Arkansas","AR","Van Buren","141","","","35.5773","-92.5456","4"],"72031":["US","72031","Clinton","Arkansas","AR","Van Buren","141","","","35.6045","-92.4758","4"],"72088":["US","72088","Fairfield Bay","Arkansas","AR","Van Buren","141","","","35.6027","-92.2742","4"],"72141":["US","72141","Scotland","Arkansas","AR","Van Buren","141","","","35.508","-92.5867","4"],"72153":["US","72153","Shirley","Arkansas","AR","Van Buren","141","","","35.6498","-92.3143","4"],"72629":["US","72629","Dennard","Arkansas","AR","Van Buren","141","","","35.7252","-92.5575","4"],"72701":["US","72701","Fayetteville","Arkansas","AR","Washington","143","","","36.052","-94.1534","4"],"72702":["US","72702","Fayetteville","Arkansas","AR","Washington","143","","","36.0626","-94.1574","4"],"72703":["US","72703","Fayetteville","Arkansas","AR","Washington","143","","","36.0992","-94.1716","4"],"72704":["US","72704","Fayetteville","Arkansas","AR","Washington","143","","","36.0877","-94.3093","4"],"72717":["US","72717","Canehill","Arkansas","AR","Washington","143","","","35.8477","-94.4441","4"],"72727":["US","72727","Elkins","Arkansas","AR","Washington","143","","","36.0177","-94.0073","4"],"72728":["US","72728","Elm Springs","Arkansas","AR","Washington","143","","","36.21","-94.2546","4"],"72729":["US","72729","Evansville","Arkansas","AR","Washington","143","","","35.7823","-94.4638","4"],"72730":["US","72730","Farmington","Arkansas","AR","Washington","143","","","36.0436","-94.2539","4"],"72735":["US","72735","Goshen","Arkansas","AR","Washington","143","","","36.0876","-93.9666","4"],"72737":["US","72737","Greenland","Arkansas","AR","Washington","143","","","35.9942","-94.1752","4"],"72741":["US","72741","Johnson","Arkansas","AR","Washington","143","","","36.1329","-94.1655","4"],"72744":["US","72744","Lincoln","Arkansas","AR","Washington","143","","","35.9569","-94.4272","4"],"72749":["US","72749","Morrow","Arkansas","AR","Washington","143","","","35.8654","-94.4432","4"],"72753":["US","72753","Prairie Grove","Arkansas","AR","Washington","143","","","35.9918","-94.3169","4"],"72762":["US","72762","Springdale","Arkansas","AR","Washington","143","","","36.1835","-94.1762","4"],"72764":["US","72764","Springdale","Arkansas","AR","Washington","143","","","36.1716","-94.0428","4"],"72765":["US","72765","Springdale","Arkansas","AR","Washington","143","","","36.1725","-94.1535","4"],"72766":["US","72766","Springdale","Arkansas","AR","Washington","143","","","36.1867","-94.1288","4"],"72769":["US","72769","Summers","Arkansas","AR","Washington","143","","","36.0138","-94.5","4"],"72770":["US","72770","Tontitown","Arkansas","AR","Washington","143","","","36.15","-94.2429","4"],"72774":["US","72774","West Fork","Arkansas","AR","Washington","143","","","35.9082","-94.2304","4"],"72959":["US","72959","Winslow","Arkansas","AR","Washington","143","","","35.8312","-94.1187","4"],"72010":["US","72010","Bald Knob","Arkansas","AR","White","145","","","35.3113","-91.5502","4"],"72012":["US","72012","Beebe","Arkansas","AR","White","145","","","35.0937","-91.9074","4"],"72020":["US","72020","Bradford","Arkansas","AR","White","145","","","35.4277","-91.519","4"],"72045":["US","72045","El Paso","Arkansas","AR","White","145","","","35.1142","-92.0901","4"],"72052":["US","72052","Garner","Arkansas","AR","White","145","","","35.1443","-91.7772","4"],"72060":["US","72060","Griffithville","Arkansas","AR","White","145","","","35.1144","-91.6242","4"],"72068":["US","72068","Higginson","Arkansas","AR","White","145","","","35.1903","-91.7108","4"],"72081":["US","72081","Judsonia","Arkansas","AR","White","145","","","35.325","-91.6491","4"],"72082":["US","72082","Kensett","Arkansas","AR","White","145","","","35.2388","-91.6731","4"],"72085":["US","72085","Letona","Arkansas","AR","White","145","","","35.3617","-91.8293","4"],"72102":["US","72102","Mc Rae","Arkansas","AR","White","145","","","35.1132","-91.8216","1"],"72121":["US","72121","Pangburn","Arkansas","AR","White","145","","","35.4216","-91.796","4"],"72136":["US","72136","Romance","Arkansas","AR","White","145","","","35.2155","-92.0699","4"],"72137":["US","72137","Rose Bud","Arkansas","AR","White","145","","","35.3214","-92.062","4"],"72139":["US","72139","Russell","Arkansas","AR","White","145","","","35.3609","-91.5071","4"],"72143":["US","72143","Searcy","Arkansas","AR","White","145","","","35.2436","-91.7317","4"],"72145":["US","72145","Searcy","Arkansas","AR","White","145","","","35.2774","-91.7326","4"],"72149":["US","72149","Searcy","Arkansas","AR","White","145","","","35.2474","-91.7314","4"],"72178":["US","72178","West Point","Arkansas","AR","White","145","","","35.2032","-91.6064","4"],"72006":["US","72006","Augusta","Arkansas","AR","Woodruff","147","","","35.2788","-91.3527","4"],"72036":["US","72036","Cotton Plant","Arkansas","AR","Woodruff","147","","","35.0178","-91.229","4"],"72059":["US","72059","Gregory","Arkansas","AR","Woodruff","147","","","35.1554","-91.3432","4"],"72074":["US","72074","Hunter","Arkansas","AR","Woodruff","147","","","35.0529","-91.1262","4"],"72101":["US","72101","Mc Crory","Arkansas","AR","Woodruff","147","","","35.2473","-91.1793","1"],"72123":["US","72123","Patterson","Arkansas","AR","Woodruff","147","","","35.2588","-91.237","4"],"72824":["US","72824","Belleville","Arkansas","AR","Yell","149","","","35.1038","-93.4518","4"],"72827":["US","72827","Bluffton","Arkansas","AR","Yell","149","","","34.9016","-93.5919","4"],"72828":["US","72828","Briggsville","Arkansas","AR","Yell","149","","","34.9161","-93.5157","4"],"72829":["US","72829","Centerville","Arkansas","AR","Yell","149","","","35.1018","-93.1773","4"],"72833":["US","72833","Danville","Arkansas","AR","Yell","149","","","35.0495","-93.3929","4"],"72834":["US","72834","Dardanelle","Arkansas","AR","Yell","149","","","35.1955","-93.1873","4"],"72838":["US","72838","Gravelly","Arkansas","AR","Yell","149","","","34.8881","-93.6802","4"],"72842":["US","72842","Havana","Arkansas","AR","Yell","149","","","35.0832","-93.5955","4"],"72853":["US","72853","Ola","Arkansas","AR","Yell","149","","","35.0309","-93.2136","4"],"72857":["US","72857","Plainview","Arkansas","AR","Yell","149","","","34.9668","-93.3099","4"],"72860":["US","72860","Rover","Arkansas","AR","Yell","149","","","34.9475","-93.4017","4"]}